{
    "\ufeffcommon_verified": "\u0b9a\u0bb0\u0bbf\u0baa\u0bbe\u0bb0\u0bcd\u0b95\u0bcd\u0b95\u0baa\u0bcd\u0baa\u0b9f\u0bcd\u0b9f\u0ba4\u0bc1",
    "common_upload_document": "\u0b86\u0bb5\u0ba3\u0ba4\u0bcd\u0ba4\u0bc8\u0baa\u0bcd \u0baa\u0ba4\u0bbf\u0bb5\u0bc7\u0bb1\u0bcd\u0bb1\u0bc1\u0b95",
    "common_upload_your_document": "\u0b89\u0b99\u0bcd\u0b95\u0bb3\u0bcd \u0b86\u0bb5\u0ba3\u0ba4\u0bcd\u0ba4\u0bc8 \u0baa\u0ba4\u0bbf\u0bb5\u0bc7\u0bb1\u0bcd\u0bb1\u0bb5\u0bc1\u0bae\u0bcd",
    "common_upload_your_document_message": "\u0b89\u0b99\u0bcd\u0b95\u0bb3\u0bcd \u0b86\u0bb5\u0ba3\u0ba4\u0bcd\u0ba4\u0bc8 \u0baa\u0bbf\u0b9f\u0bbf\u0b8e\u0baa\u0bcd \u0bb5\u0b9f\u0bbf\u0bb5\u0ba4\u0bcd\u0ba4\u0bbf\u0bb2\u0bcd \u0baa\u0ba4\u0bbf\u0bb5\u0bc7\u0bb1\u0bcd\u0bb1\u0bb5\u0bc1\u0bae\u0bcd.",
    "common_continue": "\u0b85\u0b9f\u0bc1\u0ba4\u0bcd\u0ba4\u0ba4\u0bc1",
    "common_completed": "\u0ba8\u0bbf\u0bb1\u0bc8\u0bb5\u0bc1",
    "common_pending_verification": "\u0b89\u0bb1\u0bc1\u0ba4\u0bbf\u0baa\u0bcd\u0baa\u0b9f\u0bc1\u0ba4\u0bcd\u0ba4\u0bc1\u0ba4\u0bb2\u0bc1\u0b95\u0bcd\u0b95 \u0b9a\u0bb1\u0bcd\u0bb1\u0bc1 \u0b95\u0bbe\u0ba4\u0bcd\u0ba4\u0bc1\u0bb0\u0bc1\u0b99\u0bcd\u0b95\u0bb3\u0bcd",
    "common_drag_and_drop": "\u0b89\u0b99\u0bcd\u0b95\u0bb3\u0bcd \u0b95\u0ba3\u0ba9\u0bbf\u0baf\u0bbf\u0bb2\u0bcd(computer) \u0b87\u0bb0\u0bc1\u0ba8\u0bcd\u0ba4\u0bbe\u0bb2\u0bcd \u0b87\u0bb4\u0bc1\u0ba4\u0bcd\u0ba4\u0bc1 \u0bb5\u0ba8\u0bcd\u0ba4\u0bc1 \u0b87\u0b99\u0bcd\u0b95\u0bc7 \u0bb5\u0bbf\u0b9f\u0bb5\u0bc1\u0bae\u0bcd (drag and drop)",
    "common_or": "\u0b85\u0bb2\u0bcd\u0bb2\u0ba4\u0bc1",
    "common_browse": "\u0b87\u0ba9\u0bc8\u0baf\u0ba4\u0bb3 \u0baa\u0baf\u0ba9\u0bcd\u0baa\u0bbe\u0b9f\u0bc1",
    "common_to_choose_file": "\u0b92\u0bb0\u0bc1 \u0b95\u0bcb\u0baa\u0bcd\u0baa\u0bc8 \u0ba4\u0bc7\u0bb0\u0bcd\u0bb5\u0bc1 \u0b9a\u0bc6\u0baf\u0bcd\u0baf\u0bc1\u0b99\u0bcd\u0b95\u0bb3\u0bcd",
    "common_start": "\u0ba4\u0bca\u0b9f\u0b99\u0bcd\u0b95\u0bb3\u0bcd",
    "document_types_bank_statement": "\u0bb5\u0b99\u0bcd\u0b95\u0bbf \u0b86\u0bb5\u0ba3\u0bae\u0bcd (bank statement)",
    "document_types_loan_statement": "\u0b95\u0b9f\u0ba9\u0bcd \u0b86\u0bb5\u0ba3\u0bae\u0bcd (loan statement)",
    "document_types_credit_card_statement": "\u0b95\u0b9f\u0ba9\u0bcd \u0b85\u0b9f\u0bcd\u0b9f\u0bc8 \u0b86\u0bb5\u0ba3\u0bae\u0bcd (credit card statement)",
    "document_types_utility_bill": "\u0baa\u0baf\u0ba9\u0bcd\u0baa\u0bbe\u0b9f\u0bcd\u0b9f\u0bc1 \u0bb5\u0bbf\u0bb2\u0bcd",
    "document_types_driver_license": "\u0bb5\u0bbe\u0b95\u0ba9 \u0b93\u0b9f\u0bcd\u0b9f\u0bc1\u0ba9\u0bb0\u0bcd \u0b89\u0bb0\u0bbf\u0bae\u0bae\u0bcd",
    "document_types_passport": "\u0b95\u0b9f\u0bb5\u0bc1\u0b9a\u0bcd\u0b9a\u0bc0\u0b9f\u0bcd & \u0baa\u0bbe\u0bb8\u0bcd\u0baa\u0bcb\u0b9f\u0bcd",
    "document_types_national_id": "\u0ba4\u0bc7\u0b9a\u0bbf\u0baf \u0b90\u0b9f\u0bbf",
    "document_types_pr_card": "\u0ba8\u0bbf\u0bb0\u0ba8\u0bcd\u0ba4\u0bb0 \u0bb5\u0ba4\u0bbf\u0bb5\u0bbf\u0b9f \u0b85\u0b9f\u0bcd\u0b9f\u0bc8",
    "level_level1_title": "\u0ba8\u0bbf\u0bb2\u0bc8 1 \u0b9a\u0bb0\u0bbf\u0baa\u0bbe\u0bb0\u0bcd\u0baa\u0bcd\u0baa\u0bc1",
    "level_level1_message": "\u0ba4\u0bc7\u0bb5\u0bc8\u0baf\u0bbe\u0ba9 \u0b85\u0ba9\u0bc8\u0ba4\u0bcd\u0ba4\u0bc1 \u0baa\u0b9f\u0bbf\u0b95\u0bb3\u0bc8\u0baf\u0bc1\u0bae\u0bcd \u0bae\u0bc1\u0b9f\u0bbf\u0b95\u0bcd\u0b95\u0bb5\u0bc1\u0bae\u0bcd. \u0b87\u0ba8\u0bcd\u0ba4 \u0ba8\u0bbf\u0bb2\u0bc8 \u0b9a\u0bb0\u0bbf\u0baa\u0bbe\u0bb0\u0bcd\u0baa\u0bcd\u0baa\u0bc1 \u0b89\u0b99\u0bcd\u0b95\u0bb3\u0bc8 {{daily_limit}} CAD \u0ba4\u0bbf\u0ba9\u0b9a\u0bb0\u0bbf \u0b85\u0bb2\u0bcd\u0bb2\u0ba4\u0bc1 {{monthly_limit} CAD \u0bae\u0bbe\u0ba4\u0ba4\u0bcd\u0ba4\u0bbf\u0bb1\u0bcd\u0b95\u0bc1 \u0b85\u0ba9\u0bc1\u0baa\u0bcd\u0baa \u0b85\u0ba9\u0bc1\u0bae\u0ba4\u0bbf\u0b95\u0bcd\u0b95\u0bbf\u0bb1\u0ba4\u0bc1.",
    "level_level2_title": "\u0b87\u0bb0\u0ba3\u0bcd\u0b9f\u0bbe\u0bb5\u0ba4\u0bc1 \u0bae\u0bc1\u0bb1\u0bc8\u0baf\u0bbe\u0ba9 \u0b89\u0bb1\u0bc1\u0ba4\u0bbf\u0baa\u0bcd\u0baa\u0b9f\u0bc1\u0ba4\u0bcd\u0ba4\u0bc1\u0ba4\u0bb2\u0bcd",
    "level_level2_message": "\u0ba4\u0bc7\u0bb5\u0bc8\u0baf\u0bbe\u0ba9 \u0b85\u0ba9\u0bc8\u0ba4\u0bcd\u0ba4\u0bc1 \u0baa\u0b9f\u0bbf\u0b95\u0bb3\u0bc8\u0baf\u0bc1\u0bae\u0bcd \u0bae\u0bc1\u0b9f\u0bbf\u0b95\u0bcd\u0b95\u0bb5\u0bc1\u0bae\u0bcd. \u0b87\u0ba8\u0bcd\u0ba4 \u0ba8\u0bbf\u0bb2\u0bc8 \u0b9a\u0bb0\u0bbf\u0baa\u0bbe\u0bb0\u0bcd\u0baa\u0bcd\u0baa\u0bc1 \u0b89\u0b99\u0bcd\u0b95\u0bb3\u0bc8 {{daily_limit}} CAD \u0ba4\u0bbf\u0ba9\u0b9a\u0bb0\u0bbf \u0b85\u0bb2\u0bcd\u0bb2\u0ba4\u0bc1 {{monthly_limit} CAD \u0bae\u0bbe\u0ba4\u0ba4\u0bcd\u0ba4\u0bbf\u0bb1\u0bcd\u0b95\u0bc1 \u0b85\u0ba9\u0bc1\u0baa\u0bcd\u0baa \u0b85\u0ba9\u0bc1\u0bae\u0ba4\u0bbf\u0b95\u0bcd\u0b95\u0bbf\u0bb1\u0ba4\u0bc1.",
    "level_level3_title": "\u0ba8\u0bbf\u0bb2\u0bc8 3 \u0b9a\u0bb0\u0bbf\u0baa\u0bbe\u0bb0\u0bcd\u0baa\u0bcd\u0baa\u0bc1",
    "level_level3_message": "\u0b87\u0ba8\u0bcd\u0ba4 \u0ba8\u0bbf\u0bb2\u0bc8 \u0b9a\u0bb0\u0bbf\u0baa\u0bbe\u0bb0\u0bcd\u0baa\u0bcd\u0baa\u0bc1 \u0b89\u0b99\u0bcd\u0b95\u0bb3\u0bc8 {{daily_limit}} CAD \u0ba4\u0bbf\u0ba9\u0b9a\u0bb0\u0bbf \u0b85\u0bb2\u0bcd\u0bb2\u0ba4\u0bc1 {{monthly_limit} CAD \u0bae\u0bbe\u0ba4\u0ba4\u0bcd\u0ba4\u0bbf\u0bb1\u0bcd\u0b95\u0bc1 \u0b85\u0ba9\u0bc1\u0baa\u0bcd\u0baa \u0b85\u0ba9\u0bc1\u0bae\u0ba4\u0bbf\u0b95\u0bcd\u0b95\u0bbf\u0bb1\u0ba4\u0bc1.",
    "level_level4_title": "\u0ba8\u0bbf\u0bb2\u0bc8 4 \u0b9a\u0bb0\u0bbf\u0baa\u0bbe\u0bb0\u0bcd\u0baa\u0bcd\u0baa\u0bc1",
    "level_level4_message": "\u0ba4\u0bc7\u0bb5\u0bc8\u0baf\u0bbe\u0ba9 \u0b85\u0ba9\u0bc8\u0ba4\u0bcd\u0ba4\u0bc1 \u0baa\u0b9f\u0bbf\u0b95\u0bb3\u0bc8\u0baf\u0bc1\u0bae\u0bcd \u0bae\u0bc1\u0b9f\u0bbf\u0b95\u0bcd\u0b95\u0bb5\u0bc1\u0bae\u0bcd. \u0b87\u0ba8\u0bcd\u0ba4 \u0ba8\u0bbf\u0bb2\u0bc8 \u0b9a\u0bb0\u0bbf\u0baa\u0bbe\u0bb0\u0bcd\u0baa\u0bcd\u0baa\u0bc1 \u0b89\u0b99\u0bcd\u0b95\u0bb3\u0bc8 {{daily_limit}} CAD \u0ba4\u0bbf\u0ba9\u0b9a\u0bb0\u0bbf \u0b85\u0bb2\u0bcd\u0bb2\u0ba4\u0bc1 {{monthly_limit} AD CAD \u0bae\u0bbe\u0ba4\u0ba4\u0bcd\u0ba4\u0bbf\u0bb1\u0bcd\u0b95\u0bc1 \u0b85\u0ba9\u0bc1\u0baa\u0bcd\u0baa \u0b85\u0ba9\u0bc1\u0bae\u0ba4\u0bbf\u0b95\u0bcd\u0b95\u0bbf\u0bb1\u0ba4\u0bc1.",
    "level_go_to_main_menu": "\u0baa\u0bbf\u0bb0\u0ba4\u0bbe\u0ba9 & \u0bae\u0bc6\u0baf\u0bcd\u0ba9\u0bcd \u0bae\u0bc6\u0ba9\u0bc1\u0bb5\u0bc1\u0b95\u0bcd\u0b95\u0bc1\u0b9a\u0bcd \u0b9a\u0bc6\u0bb2\u0bcd\u0bb2\u0bb5\u0bc1\u0bae\u0bcd",
    "level_send_money": "\u0baa\u0ba3\u0bae\u0bcd \u0b85\u0ba9\u0bc1\u0baa\u0bcd\u0baa\u0bb5\u0bc1\u0bae\u0bcd",
    "level_go_next_level": "\u0ba8\u0bbf\u0bb2\u0bc8 \u0b9a\u0bb0\u0bbf\u0baa\u0bbe\u0bb0\u0bcd\u0baa\u0bcd\u0baa\u0bc1\u0b95\u0bcd\u0b95\u0bc1\u0b9a\u0bcd \u0b9a\u0bc6\u0bb2\u0bcd\u0bb2\u0bb5\u0bc1\u0bae\u0bcd",
    "levels_verification_limits": "\u0b89\u0bb1\u0bc1\u0ba4\u0bbf\u0baa\u0bcd\u0baa\u0b9f\u0bc1\u0ba4\u0bcd\u0ba4\u0bc1\u0ba4\u0bb2\u0bc1\u0bae\u0bcd \u0b85\u0ba9\u0bc1\u0baa\u0bcd\u0baa\u0bc1\u0bae\u0bcd \u0b85\u0bb3\u0bb5\u0bc1\u0bae\u0bcd (verification and limits)",
    "levels_highest_level_security": "\u0b89\u0b99\u0bcd\u0b95\u0bb3\u0bcd \u0baa\u0bbe\u0ba4\u0bc1\u0b95\u0bbe\u0baa\u0bcd\u0baa\u0bc1\u0b95\u0bcd\u0b95\u0bc1\u0bae\u0bcd \u0bae\u0bb1\u0bcd\u0bb1\u0bc1\u0bae\u0bcd \u0b9a\u0b9f\u0bcd\u0b9f \u0b95\u0bbe\u0bb0\u0ba3\u0b95\u0bb3\u0bc1\u0b95\u0bcd\u0b95\u0bbe\u0b95\u0bb5\u0bc1\u0bae\u0bcd \u0ba8\u0bc0\u0b99\u0bcd\u0b95\u0bb3\u0bcd \u0b89\u0b99\u0bcd\u0b95\u0bb3\u0bc8 \u0b89\u0bb1\u0bc1\u0ba4\u0bbf\u0baa\u0bcd\u0baa\u0b9f\u0bc1\u0ba4\u0bcd\u0ba4 \u0bb5\u0bc7\u0ba3\u0bcd\u0b9f\u0bc1\u0bae\u0bcd",
    "levels_you_almost_there": "\u0ba8\u0bc0\u0b99\u0bcd\u0b95\u0bb3\u0bcd \u0b95\u0b9f\u0bc8\u0b9a\u0bbf \u0b87\u0b9f\u0ba4\u0bcd\u0ba4\u0bc1\u0b95\u0bcd\u0b95\u0bc1 \u0bb5\u0ba8\u0bcd\u0ba4\u0bc1 \u0bb5\u0bbf\u0b9f\u0bcd\u0b9f\u0bbf\u0bb0\u0bcd\u0b95\u0bb3\u0bcd",
    "levels_complete_verification_and_transaction_will_release": "\u0ba8\u0bbf\u0bb2\u0bc8\u0b9a\u0bb0\u0bbf\u0baa\u0bbe\u0bb0\u0bcd\u0baa\u0bcd\u0baa\u0bc8 \u0bae\u0bc1\u0b9f\u0bbf\u0b95\u0bcd\u0b95\u0bb5\u0bc1\u0bae\u0bcd, \u0b89\u0b99\u0bcd\u0b95\u0bb3\u0bcd \u0baa\u0bb0\u0bbf\u0bb5\u0bb0\u0bcd\u0ba4\u0bcd\u0ba4\u0ba9\u0bc8 \u0ba4\u0bbe\u0ba9\u0bbe\u0b95\u0bb5\u0bc7 \u0bae\u0bc1\u0b9f\u0bbf\u0b95\u0bcd\u0b95\u0baa\u0bcd\u0baa\u0b9f\u0bc1\u0bae\u0bcd.",
    "levels_got_it": "\u0b9a\u0bb0\u0bbf",
    "levels_level": "\u0ba8\u0bbf\u0bb2\u0bc8",
    "levels_daily_limit": "\u0ba4\u0bbf\u0ba9\u0b9a\u0bb0\u0bbf \u0bb5\u0bb0\u0bae\u0bcd\u0baa\u0bc1",
    "levels_monthly_limit": "\u0bae\u0bbe\u0ba4 \u0bb5\u0bb0\u0bae\u0bcd\u0baa\u0bc1",
    "levels_coming_soon": "\u0bb5\u0bbf\u0bb0\u0bc8\u0bb5\u0bbf\u0bb2\u0bcd",
    "levels_start": "\u0ba4\u0bca\u0b9f\u0b99\u0bcd\u0b95\u0bc1",
    "fields_personal_info_title": "\u0ba4\u0ba9\u0bbf\u0baa\u0bcd\u0baa\u0b9f\u0bcd\u0b9f \u0ba4\u0b95\u0bb5\u0bb2\u0bcd",
    "fields_personal_info_message": "\u0ba4\u0baf\u0bb5\u0bc1\u0b9a\u0bc6\u0baf\u0bcd\u0ba4\u0bc1, \u0b89\u0b99\u0bcd\u0b95\u0bb3\u0bc1\u0b95\u0bcd\u0b95\u0bc1 \u0ba4\u0ba9\u0bbf\u0baa\u0bcd\u0baa\u0b9f\u0bcd\u0b9f \u0ba4\u0b95\u0bb5\u0bb2\u0bcd\u0b95\u0bb3\u0bc8 \u0b8e\u0b99\u0bcd\u0b95\u0bb3\u0bc1\u0b95\u0bcd\u0b95\u0bc1 \u0bb5\u0bb4\u0b99\u0bcd\u0b95\u0bb5\u0bc1\u0bae\u0bcd, \u0b8e\u0ba9\u0bb5\u0bc7 \u0b89\u0b99\u0bcd\u0b95\u0bb3\u0bcd \u0b85\u0b9f\u0bc8\u0baf\u0bbe\u0bb3\u0ba4\u0bcd\u0ba4\u0bc8 \u0ba8\u0bbe\u0b99\u0bcd\u0b95\u0bb3\u0bcd \u0b9a\u0bb0\u0bbf\u0baa\u0bbe\u0bb0\u0bcd\u0b95\u0bcd\u0b95 \u0bae\u0bc1\u0b9f\u0bbf\u0baf\u0bc1\u0bae\u0bcd, \u0bae\u0bc7\u0bb2\u0bc1\u0bae\u0bcd \u0b89\u0b99\u0bcd\u0b95\u0bb3\u0bcd \u0baa\u0ba3\u0bae\u0bcd \u0bae\u0bb1\u0bcd\u0bb1\u0bc1\u0bae\u0bcd \u0ba4\u0bb0\u0bb5\u0bc1 \u0baa\u0bbe\u0ba4\u0bc1\u0b95\u0bbe\u0baa\u0bcd\u0baa\u0bbf\u0ba9\u0bcd \u0bae\u0bbf\u0b95 \u0b89\u0baf\u0bb0\u0bcd\u0ba8\u0bcd\u0ba4 \u0bae\u0b9f\u0bcd\u0b9f\u0ba4\u0bcd\u0ba4\u0bc8 \u0bb5\u0bb4\u0b99\u0bcd\u0b95 \u0bae\u0bc1\u0b9f\u0bbf\u0baf\u0bc1\u0bae\u0bcd.",
    "fields_personal_info_fill_personal_info": "\u0ba4\u0ba9\u0bbf\u0baa\u0bcd\u0baa\u0b9f\u0bcd\u0b9f \u0ba4\u0b95\u0bb5\u0bb2\u0bc8 \u0ba8\u0bbf\u0bb0\u0baa\u0bcd\u0baa\u0bb5\u0bc1\u0bae\u0bcd",
    "fields_personal_info_personal_info_dialog_title": "\u0b89\u0b99\u0bcd\u0b95\u0bb3\u0bc8 \u0baa\u0bb1\u0bcd\u0bb1\u0bbf \u0b95\u0bca\u0b9e\u0bcd\u0b9a\u0bae\u0bcd \u0b9a\u0bca\u0bb2\u0bcd\u0bb2\u0bc1\u0b99\u0bcd\u0b95\u0bb3\u0bcd (about you)",
    "fields_personal_info_personal_info_dialog_section_personalinfo": "\u0b89\u0b99\u0bcd\u0b95\u0bb3\u0bcd \u0ba4\u0ba9\u0bbf\u0baa\u0bcd\u0baa\u0b9f\u0bcd\u0b9f \u0ba4\u0b95\u0bb5\u0bb2\u0bcd",
    "fields_personal_info_personal_info_dialog_section_address": "\u0b89\u0b99\u0bcd\u0b95\u0bb3\u0bcd \u0bae\u0bc1\u0b95\u0bb5\u0bb0\u0bbf",
    "fields_personal_info_personal_info_dialog_section_occupation_industry": "\u0b89\u0b99\u0bcd\u0b95\u0bb3\u0bcd \u0bb5\u0bc7\u0bb2\u0bc8 \u0b8e\u0ba9\u0bcd\u0ba9",
    "fields_personal_info_successfully_submitted": "\u0b89\u0b99\u0bcd\u0b95\u0bb3\u0bcd \u0ba4\u0ba9\u0bbf\u0baa\u0bcd\u0baa\u0b9f\u0bcd\u0b9f \u0ba4\u0b95\u0bb5\u0bb2\u0bcd\u0b95\u0bb3\u0bcd \u0bb5\u0bc6\u0bb1\u0bcd\u0bb1\u0bbf\u0b95\u0bb0\u0bae\u0bbe\u0b95 \u0b9a\u0bae\u0bb0\u0bcd\u0baa\u0bcd\u0baa\u0bbf\u0b95\u0bcd\u0b95\u0baa\u0bcd\u0baa\u0b9f\u0bcd\u0b9f\u0ba9",
    "fields_personal_info_occupation": "\u0b89\u0b99\u0bcd\u0b95\u0bb3\u0bcd \u0bb5\u0bc7\u0bb2\u0bc8 \u0b8e\u0ba9\u0bcd\u0ba9",
    "fields_personal_info_first_name": "\u0bae\u0bc1\u0ba4\u0bb2\u0bcd \u0baa\u0bc6\u0baf\u0bb0\u0bcd(First name)",
    "fields_personal_info_last_name": "\u0b85\u0baa\u0bcd\u0baa\u0bbe\u0bb5\u0bbf\u0ba9\u0bcd \u0baa\u0bc6\u0baf\u0bb0\u0bcd (Last name)",
    "fields_personal_info_date_of_birth": "\u0b89\u0b99\u0bcd\u0b95\u0bb3\u0bcd \u0baa\u0bbf\u0bb1\u0ba8\u0bcd\u0ba4 \u0ba4\u0bc7\u0ba4\u0bbf \u0b8e\u0ba9\u0bcd\u0ba9 (your date of birth)",
    "fields_personal_info_address": "\u0bae\u0bc1\u0b95\u0bb5\u0bb0\u0bbf",
    "fields_personal_info_unit_number": "\u0baf\u0bc1\u0ba9\u0bbf\u0b9f\u0bcd \u0ba8\u0bae\u0bcd\u0baa\u0bb0\u0bcd (\u0bb5\u0bbf\u0bb0\u0bc1\u0bae\u0bcd\u0baa\u0bbf\u0ba9\u0bbe\u0bb2\u0bcd)",
    "fields_personal_info_province": "\u0bae\u0bbe\u0b95\u0bbe\u0ba3\u0bae\u0bcd",
    "fields_personal_info_city": "\u0b89\u0b99\u0bcd\u0b95\u0bb3\u0bcd \u0ba8\u0b95\u0bb0\u0ba4\u0bcd\u0ba4\u0bbf\u0ba9\u0bcd \u0baa\u0bc6\u0baf\u0bb0\u0bcd",
    "fields_personal_info_postal_code": "\u0b85\u0b9e\u0bcd\u0b9a\u0bb2\u0bcd \u0b95\u0bc1\u0bb1\u0bbf\u0baf\u0bc0\u0b9f\u0bc1 ( Postal code )",
    "fields_personal_info_country": "\u0ba8\u0bbe\u0b9f\u0bc1",
    "fields_personal_info_postal_code_error": "\u0b9a\u0bb0\u0bbf\u0baf\u0bbe\u0ba9 \u0b85\u0b9e\u0bcd\u0b9a\u0bb2\u0bcd \u0b95\u0bc1\u0bb1\u0bbf\u0baf\u0bc0\u0b9f\u0bcd\u0b9f\u0bc8 \u0b89\u0bb3\u0bcd\u0bb3\u0bbf\u0b9f\u0bb5\u0bc1\u0bae\u0bcd",
    "fields_personal_info_phone_number": "\u0ba4\u0bca\u0bb2\u0bc8\u0baa\u0bc7\u0b9a\u0bbf \u0b87\u0bb2\u0b95\u0bcd\u0b95\u0bae\u0bcd",
    "fields_phone_verification_title": "\u0ba4\u0bca\u0bb2\u0bc8\u0baa\u0bc7\u0b9a\u0bbf \u0b8e\u0ba3\u0bcd \u0b9a\u0bb0\u0bbf\u0baa\u0bbe\u0bb0\u0bcd\u0baa\u0bcd\u0baa\u0bc1",
    "fields_phone_verification_message": "\u0ba4\u0baf\u0bb5\u0bc1\u0b9a\u0bc6\u0baf\u0bcd\u0ba4\u0bc1, \u0b89\u0b99\u0bcd\u0b95\u0bb3\u0bc1\u0b9f\u0bc8\u0baf \u0ba4\u0bca\u0bb2\u0bc8\u0baa\u0bc7\u0b9a\u0bbf \u0b8e\u0ba3\u0bcd\u0ba3\u0bc8 \u0b8e\u0b99\u0bcd\u0b95\u0bb3\u0bc1\u0b95\u0bcd\u0b95\u0bc1 \u0bb5\u0bb4\u0b99\u0bcd\u0b95\u0bb5\u0bc1\u0bae\u0bcd, \u0b8e\u0ba9\u0bb5\u0bc7 \u0b89\u0b99\u0bcd\u0b95\u0bb3\u0bcd \u0baa\u0ba3\u0bae\u0bcd \u0bae\u0bb1\u0bcd\u0bb1\u0bc1\u0bae\u0bcd \u0ba4\u0bb0\u0bb5\u0bc1 \u0baa\u0bbe\u0ba4\u0bc1\u0b95\u0bbe\u0baa\u0bcd\u0baa\u0bbf\u0ba9\u0bcd \u0bae\u0bbf\u0b95 \u0b89\u0baf\u0bb0\u0bcd\u0ba8\u0bcd\u0ba4 \u0ba8\u0bbf\u0bb2\u0bc8\u0baf\u0bc8 \u0bb5\u0bb4\u0b99\u0bcd\u0b95 \u0b85\u0ba4\u0bc8 \u0ba8\u0bbe\u0b99\u0bcd\u0b95\u0bb3\u0bcd \u0b9a\u0bb0\u0bbf\u0baa\u0bbe\u0bb0\u0bcd\u0b95\u0bcd\u0b95 \u0bae\u0bc1\u0b9f\u0bbf\u0baf\u0bc1\u0bae\u0bcd",
    "fields_phone_verification_start_phone_number_verification": "\u0ba4\u0bca\u0bb2\u0bc8\u0baa\u0bc7\u0b9a\u0bbf \u0b8e\u0ba3\u0bcd \u0b9a\u0bb0\u0bbf\u0baa\u0bbe\u0bb0\u0bcd\u0baa\u0bcd\u0baa\u0bc8\u0ba4\u0bcd \u0ba4\u0bca\u0b9f\u0b99\u0bcd\u0b95\u0bb5\u0bc1\u0bae\u0bcd",
    "fields_phone_verification_successfully_verified_title": "\u0b89\u0b99\u0bcd\u0b95\u0bb3\u0bcd \u0b9a\u0bb0\u0bbf\u0baa\u0bbe\u0bb0\u0bcd\u0baa\u0bcd\u0baa\u0bc1\u0b95\u0bcd\u0b95\u0bc1 \u0ba8\u0ba9\u0bcd\u0bb1\u0bbf",
    "fields_phone_verification_successfully_verified_message": "\u0b89\u0b99\u0bcd\u0b95\u0bb3\u0bcd \u0ba4\u0bca\u0bb2\u0bc8\u0baa\u0bc7\u0b9a\u0bbf \u0b8e\u0ba3\u0bcd \u0bb5\u0bc6\u0bb1\u0bcd\u0bb1\u0bbf\u0b95\u0bb0\u0bae\u0bbe\u0b95 \u0b9a\u0bb0\u0bbf\u0baa\u0bbe\u0bb0\u0bcd\u0b95\u0bcd\u0b95\u0baa\u0bcd\u0baa\u0b9f\u0bcd\u0b9f\u0ba4\u0bc1.",
    "fields_email_verification_title": "\u0bae\u0bbf\u0ba9\u0bcd\u0ba9\u0b9e\u0bcd\u0b9a\u0bb2\u0bcd \u0b9a\u0bb0\u0bbf\u0baa\u0bbe\u0bb0\u0bcd\u0baa\u0bcd\u0baa\u0bc1",
    "fields_email_verification_message": "\u0b89\u0b99\u0bcd\u0b95\u0bb3\u0bcd \u0b95\u0ba3\u0b95\u0bcd\u0b95\u0bc8\u0b9a\u0bcd \u0b9a\u0bc6\u0baf\u0bb2\u0bcd\u0baa\u0b9f\u0bc1\u0ba4\u0bcd\u0ba4 \u0b89\u0b99\u0bcd\u0b95\u0bb3\u0bcd \u0bae\u0bbf\u0ba9\u0bcd\u0ba9\u0b9e\u0bcd\u0b9a\u0bb2\u0bcd \u0bae\u0bc1\u0b95\u0bb5\u0bb0\u0bbf\u0baf\u0bc8\u0b9a\u0bcd \u0b9a\u0bb0\u0bbf\u0baa\u0bbe\u0bb0\u0bcd\u0b95\u0bcd\u0b95\u0bb5\u0bc1\u0bae\u0bcd.",
    "fields_email_verification_re_send_email": "\u0bae\u0bbf\u0ba9\u0bcd\u0ba9\u0b9e\u0bcd\u0b9a\u0bb2\u0bcd \u0bae\u0bc0\u0ba3\u0bcd\u0b9f\u0bc1\u0bae\u0bcd \u0b85\u0ba9\u0bc1\u0baa\u0bcd\u0baa\u0bb5\u0bc1\u0bae\u0bcd",
    "fields_email_verification_successfully_verified_title": "\u0bae\u0bbf\u0ba9\u0bcd\u0ba9\u0b9e\u0bcd\u0b9a\u0bb2\u0bcd \u0b85\u0ba9\u0bc1\u0baa\u0bcd\u0baa\u0baa\u0bcd\u0baa\u0b9f\u0bcd\u0b9f\u0ba4\u0bc1",
    "fields_email_verification_successfully_verified_message": "\u0b9a\u0bb0\u0bbf\u0baa\u0bbe\u0bb0\u0bcd\u0baa\u0bcd\u0baa\u0bc1 \u0bae\u0bbf\u0ba9\u0bcd\u0ba9\u0b9e\u0bcd\u0b9a\u0bb2\u0bcd \u0b89\u0b99\u0bcd\u0b95\u0bb3\u0bcd \u0bae\u0bbf\u0ba9\u0bcd\u0ba9\u0b9e\u0bcd\u0b9a\u0bb2\u0bcd \u0bae\u0bc1\u0b95\u0bb5\u0bb0\u0bbf\u0b95\u0bcd\u0b95\u0bc1 \u0bb5\u0bc6\u0bb1\u0bcd\u0bb1\u0bbf\u0b95\u0bb0\u0bae\u0bbe\u0b95 \u0b85\u0ba9\u0bc1\u0baa\u0bcd\u0baa\u0baa\u0bcd\u0baa\u0b9f\u0bcd\u0b9f\u0ba4\u0bc1",
    "fields_email_verification_dialog_txt_label": "\u0ba4\u0baf\u0bb5\u0bc1\u0b9a\u0bc6\u0baf\u0bcd\u0ba4\u0bc1 \u0b89\u0b99\u0bcd\u0b95\u0bb3\u0bcd \u0bae\u0bbf\u0ba9\u0bcd\u0ba9\u0b9e\u0bcd\u0b9a\u0bb2\u0bcd \u0bae\u0bc1\u0b95\u0bb5\u0bb0\u0bbf\u0baf\u0bc8 \u0b89\u0bb3\u0bcd\u0bb3\u0bbf\u0b9f\u0bb5\u0bc1\u0bae\u0bcd",
    "fields_email_verification_send_verification_email": "\u0b9a\u0bb0\u0bbf\u0baa\u0bbe\u0bb0\u0bcd\u0baa\u0bcd\u0baa\u0bc1 \u0bae\u0bbf\u0ba9\u0bcd\u0ba9\u0b9e\u0bcd\u0b9a\u0bb2\u0bcd \u0b85\u0ba9\u0bc1\u0baa\u0bcd\u0baa\u0bb5\u0bc1\u0bae\u0bcd",
    "fields_employment_verification_title": "\u0bb5\u0bc7\u0bb2\u0bc8\u0bb5\u0bbe\u0baf\u0bcd\u0baa\u0bcd\u0baa\u0bc1 \u0ba4\u0b95\u0bb5\u0bb2\u0bcd",
    "fields_employment_verification_message": "\u0b89\u0b99\u0bcd\u0b95\u0bb3\u0bbf\u0b9f\u0bae\u0bcd \u0b9a\u0b9f\u0bcd\u0b9f\u0baa\u0bc2\u0bb0\u0bcd\u0bb5\u0bae\u0bbe\u0ba9 \u0bb5\u0bb0\u0bc1\u0bae\u0bbe\u0ba9 \u0b86\u0ba4\u0bbe\u0bb0\u0bae\u0bcd \u0b87\u0bb0\u0bc1\u0baa\u0bcd\u0baa\u0ba4\u0bc8 \u0b89\u0bb1\u0bc1\u0ba4\u0bbf\u0baa\u0bcd\u0baa\u0b9f\u0bc1\u0ba4\u0bcd\u0ba4, \u0b89\u0b99\u0bcd\u0b95\u0bb3\u0bcd \u0bb5\u0bc7\u0bb2\u0bc8\u0bb5\u0bbe\u0baf\u0bcd\u0baa\u0bcd\u0baa\u0bc1 \u0b95\u0bc1\u0bb1\u0bbf\u0ba4\u0bcd\u0ba4\u0bc1 \u0b8e\u0b99\u0bcd\u0b95\u0bb3\u0bc1\u0b95\u0bcd\u0b95\u0bc1 \u0b95\u0bc2\u0b9f\u0bc1\u0ba4\u0bb2\u0bcd \u0ba4\u0b95\u0bb5\u0bb2\u0bcd\u0b95\u0bb3\u0bcd \u0ba4\u0bc7\u0bb5\u0bc8. \u0b8e\u0bb2\u0bcd\u0bb2\u0bbe \u0ba4\u0b95\u0bb5\u0bb2\u0bcd\u0b95\u0bb3\u0bc1\u0bae\u0bcd \u0baa\u0bbe\u0ba4\u0bc1\u0b95\u0bbe\u0b95\u0bcd\u0b95\u0baa\u0bcd\u0baa\u0b9f\u0bc1\u0bae\u0bcd, \u0baf\u0bbe\u0bb0\u0bc1\u0b9f\u0ba9\u0bc1\u0bae\u0bcd \u0baa\u0b95\u0bbf\u0bb0\u0baa\u0bcd\u0baa\u0b9f\u0bbe\u0ba4\u0bc1.",
    "fields_employment_verification_re_send_email": "\u0bae\u0bbf\u0ba9\u0bcd\u0ba9\u0b9e\u0bcd\u0b9a\u0bb2\u0bcd \u0bae\u0bc0\u0ba3\u0bcd\u0b9f\u0bc1\u0bae\u0bcd \u0b85\u0ba9\u0bc1\u0baa\u0bcd\u0baa\u0bb5\u0bc1\u0bae\u0bcd",
    "fields_employment_verification_successfully_verified_title": "\u0b9a\u0bae\u0bb0\u0bcd\u0baa\u0bcd\u0baa\u0bbf\u0ba4\u0bcd\u0ba4\u0ba4\u0bb1\u0bcd\u0b95\u0bc1 \u0ba8\u0ba9\u0bcd\u0bb1\u0bbf!",
    "fields_employment_verification_successfully_verified_message": "\u0b89\u0b99\u0bcd\u0b95\u0bb3\u0bcd \u0ba4\u0b95\u0bb5\u0bb2\u0bcd \u0bb5\u0bc6\u0bb1\u0bcd\u0bb1\u0bbf\u0b95\u0bb0\u0bae\u0bbe\u0b95 \u0b9a\u0bc6\u0baf\u0bb2\u0bbe\u0b95\u0bcd\u0b95\u0baa\u0bcd\u0baa\u0b9f\u0bcd\u0b9f\u0ba4\u0bc1, \u0b85\u0b9f\u0bc1\u0ba4\u0bcd\u0ba4 24 \u0bae\u0ba3\u0bbf \u0ba8\u0bc7\u0bb0\u0ba4\u0bcd\u0ba4\u0bbf\u0bb2\u0bcd \u0b8e\u0b99\u0bcd\u0b95\u0bb3\u0bcd \u0b86\u0ba4\u0bb0\u0bb5\u0bc1 \u0b95\u0bc1\u0bb4\u0bc1 \u0b85\u0ba4\u0bc8 \u0b9a\u0bb0\u0bbf\u0baa\u0bbe\u0bb0\u0bcd\u0b95\u0bcd\u0b95\u0bc1\u0bae\u0bcd.",
    "fields_employment_verification_dialog_message": "\u0ba4\u0baf\u0bb5\u0bc1\u0b9a\u0bc6\u0baf\u0bcd\u0ba4\u0bc1, \u0b89\u0b99\u0bcd\u0b95\u0bb3\u0bcd \u0bb5\u0bc7\u0bb2\u0bc8\u0bb5\u0bbe\u0baf\u0bcd\u0baa\u0bcd\u0baa\u0bc1 \u0ba4\u0b95\u0bb5\u0bb2\u0bcd\u0b95\u0bb3\u0bc8 \u0b8e\u0b99\u0bcd\u0b95\u0bb3\u0bc1\u0b95\u0bcd\u0b95\u0bc1 \u0bb5\u0bb4\u0b99\u0bcd\u0b95\u0bb5\u0bc1\u0bae\u0bcd, \u0b87\u0ba4\u0ba9\u0bbe\u0bb2\u0bcd \u0b89\u0b99\u0bcd\u0b95\u0bb3\u0bcd \u0baa\u0ba3\u0bae\u0bcd \u0baa\u0bbe\u0ba4\u0bc1\u0b95\u0bbe\u0baa\u0bcd\u0baa\u0bbe\u0b95 \u0b87\u0bb0\u0bc1\u0baa\u0bcd\u0baa\u0ba4\u0bc8 \u0ba8\u0bbe\u0b99\u0bcd\u0b95\u0bb3\u0bcd \u0b89\u0bb1\u0bc1\u0ba4\u0bbf\u0baa\u0bcd\u0baa\u0b9f\u0bc1\u0ba4\u0bcd\u0ba4 \u0bae\u0bc1\u0b9f\u0bbf\u0baf\u0bc1\u0bae\u0bcd.",
    "fields_employment_verification_dialog_txt_label": "\u0ba4\u0baf\u0bb5\u0bc1\u0b9a\u0bc6\u0baf\u0bcd\u0ba4\u0bc1 \u0b89\u0b99\u0bcd\u0b95\u0bb3\u0bcd \u0bae\u0bbf\u0ba9\u0bcd\u0ba9\u0b9e\u0bcd\u0b9a\u0bb2\u0bcd \u0bae\u0bc1\u0b95\u0bb5\u0bb0\u0bbf\u0baf\u0bc8 \u0b89\u0bb3\u0bcd\u0bb3\u0bbf\u0b9f\u0bb5\u0bc1\u0bae\u0bcd",
    "fields_employment_verification_fill_information": "\u0ba4\u0b95\u0bb5\u0bb2\u0bc8 \u0ba8\u0bbf\u0bb0\u0baa\u0bcd\u0baa\u0bc1\u0b95",
    "fields_document_verification_address_proof": "\u0bae\u0bc1\u0b95\u0bb5\u0bb0\u0bbf \u0b9a\u0bbe\u0ba9\u0bcd\u0bb1\u0bc1",
    "fields_document_verification_address_proof_message": "\u0ba4\u0baf\u0bb5\u0bc1\u0b9a\u0bc6\u0baf\u0bcd\u0ba4\u0bc1, \u0b89\u0b99\u0bcd\u0b95\u0bb3\u0bcd \u0baa\u0baf\u0ba9\u0bcd\u0baa\u0bbe\u0b9f\u0bcd\u0b9f\u0bc1 \u0baa\u0bbf\u0bb2\u0bcd\u0b95\u0bb3\u0bbf\u0bb2\u0bcd \u0b92\u0ba9\u0bcd\u0bb1\u0bc8 PDF \u0b85\u0bb2\u0bcd\u0bb2\u0ba4\u0bc1 \u0b9f\u0bbf\u0b9c\u0bbf\u0b9f\u0bcd\u0b9f\u0bb2\u0bcd \u0bb8\u0bcd\u0b95\u0bbf\u0bb0\u0bc0\u0ba9\u0bcd\u0bb7\u0bbe\u0b9f\u0bcd \u0bb5\u0b9f\u0bbf\u0bb5\u0ba4\u0bcd\u0ba4\u0bbf\u0bb2\u0bcd \u0baa\u0ba4\u0bbf\u0bb5\u0bc7\u0bb1\u0bcd\u0bb1\u0bb5\u0bc1\u0bae\u0bcd. \u0bb9\u0bc8\u0b9f\u0bcd\u0bb0\u0bcb, \u0b8e\u0bb0\u0bbf\u0bb5\u0bbe\u0baf\u0bc1, \u0ba8\u0bc0\u0bb0\u0bcd, \u0b87\u0ba3\u0bc8\u0baf\u0bae\u0bcd \u0b85\u0bb2\u0bcd\u0bb2\u0ba4\u0bc1 \u0bae\u0bca\u0baa\u0bc8\u0bb2\u0bcd \u0baa\u0bcb\u0ba9\u0bcd \u0baa\u0bbf\u0bb2\u0bcd\u0b95\u0bb3\u0bc8 \u0ba8\u0bbe\u0b99\u0bcd\u0b95\u0bb3\u0bcd \u0b8f\u0bb1\u0bcd\u0bb1\u0bc1\u0b95\u0bcd\u0b95\u0bca\u0bb3\u0bcd\u0b95\u0bbf\u0bb1\u0bcb\u0bae\u0bcd. \u0b89\u0b99\u0bcd\u0b95\u0bb3\u0bcd \u0bb5\u0bc0\u0b9f\u0bcd\u0b9f\u0bc1 \u0bae\u0bc1\u0b95\u0bb5\u0bb0\u0bbf \u0bae\u0bb1\u0bcd\u0bb1\u0bc1\u0bae\u0bcd \u0ba4\u0ba9\u0bbf\u0baa\u0bcd\u0baa\u0b9f\u0bcd\u0b9f \u0ba4\u0b95\u0bb5\u0bb2\u0bcd\u0b95\u0bb3\u0bcd \u0bae\u0b9a\u0bcb\u0ba4\u0bbe\u0bb5\u0bbf\u0bb2\u0bcd \u0b87\u0bb0\u0bc1\u0baa\u0bcd\u0baa\u0ba4\u0bc8 \u0b89\u0bb1\u0bc1\u0ba4\u0bbf\u0baa\u0bcd\u0baa\u0b9f\u0bc1\u0ba4\u0bcd\u0ba4\u0bbf\u0b95\u0bcd \u0b95\u0bca\u0bb3\u0bcd\u0bb3\u0bc1\u0b99\u0bcd\u0b95\u0bb3\u0bcd.",
    "fields_document_verification_bank_proof": "\u0b89\u0b99\u0bcd\u0b95\u0bb3\u0bcd \u0bb5\u0b99\u0bcd\u0b95\u0bbf\u0baf\u0bc8 \u0b89\u0bb1\u0bc1\u0ba4\u0bbf\u0baa\u0bcd\u0baa\u0b9f\u0bc1\u0ba4\u0bcd\u0ba4\u0bc1\u0ba4\u0bb2\u0bcd",
    "fields_document_verification_bank_proof_message": "\u0ba4\u0baf\u0bb5\u0bc1\u0b9a\u0bc6\u0baf\u0bcd\u0ba4\u0bc1, \u0b89\u0b99\u0bcd\u0b95\u0bb3\u0bcd \u0bb5\u0b99\u0bcd\u0b95\u0bbf \u0b85\u0bb1\u0bbf\u0b95\u0bcd\u0b95\u0bc8\u0b95\u0bb3\u0bbf\u0bb2\u0bcd \u0b92\u0ba9\u0bcd\u0bb1\u0bc8 PDF \u0b85\u0bb2\u0bcd\u0bb2\u0ba4\u0bc1 \u0b9f\u0bbf\u0b9c\u0bbf\u0b9f\u0bcd\u0b9f\u0bb2\u0bcd \u0bb8\u0bcd\u0b95\u0bbf\u0bb0\u0bc0\u0ba9\u0bcd\u0bb7\u0bbe\u0b9f\u0bcd \u0bb5\u0b9f\u0bbf\u0bb5\u0ba4\u0bcd\u0ba4\u0bbf\u0bb2\u0bcd \u0baa\u0ba4\u0bbf\u0bb5\u0bc7\u0bb1\u0bcd\u0bb1\u0bb5\u0bc1\u0bae\u0bcd. \u0b89\u0b99\u0bcd\u0b95\u0bb3\u0bcd \u0bb5\u0bc0\u0b9f\u0bcd\u0b9f\u0bc1 \u0bae\u0bc1\u0b95\u0bb5\u0bb0\u0bbf \u0bae\u0bb1\u0bcd\u0bb1\u0bc1\u0bae\u0bcd \u0ba4\u0ba9\u0bbf\u0baa\u0bcd\u0baa\u0b9f\u0bcd\u0b9f \u0ba4\u0b95\u0bb5\u0bb2\u0bcd\u0b95\u0bb3\u0bcd \u0bae\u0b9a\u0bcb\u0ba4\u0bbe\u0bb5\u0bbf\u0bb2\u0bcd \u0b87\u0bb0\u0bc1\u0baa\u0bcd\u0baa\u0ba4\u0bc8 \u0b89\u0bb1\u0bc1\u0ba4\u0bbf\u0baa\u0bcd\u0baa\u0b9f\u0bc1\u0ba4\u0bcd\u0ba4\u0bbf\u0b95\u0bcd \u0b95\u0bca\u0bb3\u0bcd\u0bb3\u0bc1\u0b99\u0bcd\u0b95\u0bb3\u0bcd.",
    "fields_document_verification_birth_proof": "\u0baa\u0bbf\u0bb1\u0ba8\u0bcd\u0ba4 \u0ba4\u0bc7\u0ba4\u0bbf\u0b95\u0bcd\u0b95\u0bbe\u0ba9 \u0b9a\u0bbe\u0ba9\u0bcd\u0bb1\u0bc1",
    "fields_document_verification_birth_proof_message": "\u0ba4\u0baf\u0bb5\u0bc1\u0b9a\u0bc6\u0baf\u0bcd\u0ba4\u0bc1, \u0b89\u0b99\u0bcd\u0b95\u0bb3\u0bcd \u0baa\u0bbf\u0bb1\u0ba8\u0bcd\u0ba4 \u0ba4\u0bc7\u0ba4\u0bbf\u0baf\u0bc8\u0b95\u0bcd \u0b95\u0bca\u0ba3\u0bcd\u0b9f \u0b85\u0ba4\u0bbf\u0b95\u0bbe\u0bb0\u0baa\u0bcd\u0baa\u0bc2\u0bb0\u0bcd\u0bb5 \u0b86\u0bb5\u0ba3\u0ba4\u0bcd\u0ba4\u0bbf\u0ba9\u0bcd \u0baa\u0bc1\u0b95\u0bc8\u0baa\u0bcd\u0baa\u0b9f\u0ba4\u0bcd\u0ba4\u0bc8\u0baa\u0bcd \u0baa\u0ba4\u0bbf\u0bb5\u0bc7\u0bb1\u0bcd\u0bb1\u0bb5\u0bc1\u0bae\u0bcd. \u0b85\u0bb0\u0b9a\u0bbe\u0b99\u0bcd\u0b95\u0ba4\u0bcd\u0ba4\u0bbe\u0bb2\u0bcd \u0bb5\u0bb4\u0b99\u0bcd\u0b95\u0baa\u0bcd\u0baa\u0b9f\u0bcd\u0b9f \u0b93\u0b9f\u0bcd\u0b9f\u0bc1\u0ba8\u0bb0\u0bcd \u0b89\u0bb0\u0bbf\u0bae\u0bae\u0bcd, \u0baa\u0bc1\u0b95\u0bc8\u0baa\u0bcd\u0baa\u0b9f \u0b85\u0b9f\u0bcd\u0b9f\u0bc8, \u0b9a\u0bc1\u0b95\u0bbe\u0ba4\u0bbe\u0bb0 \u0b85\u0b9f\u0bcd\u0b9f\u0bc8, \u0baa\u0bbf.\u0b86\u0bb0\u0bcd \u0b95\u0bbe\u0bb0\u0bcd\u0b9f\u0bc1 \u0b85\u0bb2\u0bcd\u0bb2\u0ba4\u0bc1 \u0baa\u0bbe\u0bb8\u0bcd\u0baa\u0bcb\u0bb0\u0bcd\u0b9f\u0bcd\u0b9f\u0bbf\u0ba9\u0bcd \u0baa\u0bc1\u0b95\u0bc8\u0baa\u0bcd\u0baa\u0b9f\u0ba4\u0bcd\u0ba4\u0bc8 \u0ba8\u0bc0\u0b99\u0bcd\u0b95\u0bb3\u0bcd \u0b8e\u0b9f\u0bc1\u0b95\u0bcd\u0b95\u0bb2\u0bbe\u0bae\u0bcd. \u0b8e\u0bb2\u0bcd\u0bb2\u0bbe \u0ba4\u0b95\u0bb5\u0bb2\u0bcd\u0b95\u0bb3\u0bc1\u0bae\u0bcd \u0ba4\u0bc6\u0bb0\u0bbf\u0baf\u0bc1\u0bae\u0bcd \u0b8e\u0ba9\u0bcd\u0baa\u0ba4\u0bc8\u0baf\u0bc1\u0bae\u0bcd \u0baa\u0bc1\u0b95\u0bc8\u0baa\u0bcd\u0baa\u0b9f\u0ba4\u0bcd\u0ba4\u0bbf\u0bb1\u0bcd\u0b95\u0bc1 \u0ba8\u0bb2\u0bcd\u0bb2 \u0ba4\u0bb0\u0bae\u0bcd \u0b87\u0bb0\u0bc1\u0baa\u0bcd\u0baa\u0ba4\u0bc8\u0baf\u0bc1\u0bae\u0bcd \u0b89\u0bb1\u0bc1\u0ba4\u0bbf\u0baa\u0bcd\u0baa\u0b9f\u0bc1\u0ba4\u0bcd\u0ba4\u0bbf\u0b95\u0bcd \u0b95\u0bca\u0bb3\u0bcd\u0bb3\u0bc1\u0b99\u0bcd\u0b95\u0bb3\u0bcd.",
    "fields_document_verification_tax_proof": "\u0bb5\u0bb0\u0bbf \u0ba4\u0b95\u0bb5\u0bb2\u0bcd",
    "fields_document_verification_tax_proof_message": "\u0ba4\u0baf\u0bb5\u0bc1\u0b9a\u0bc6\u0baf\u0bcd\u0ba4\u0bc1, \u0bae\u0bc1\u0ba8\u0bcd\u0ba4\u0bc8\u0baf \u0b86\u0ba3\u0bcd\u0b9f\u0bbf\u0bb2\u0bbf\u0bb0\u0bc1\u0ba8\u0bcd\u0ba4\u0bc1 \u0b89\u0b99\u0bcd\u0b95\u0bb3\u0bcd T4 \u0b85\u0bb1\u0bbf\u0b95\u0bcd\u0b95\u0bc8\u0baf\u0bbf\u0ba9\u0bcd PDF \u0ba8\u0b95\u0bb2\u0bc8\u0baa\u0bcd \u0baa\u0ba4\u0bbf\u0bb5\u0bc7\u0bb1\u0bcd\u0bb1\u0bb5\u0bc1\u0bae\u0bcd.",
    "fields_document_verification_tax_proof_dialog_title": "\u0bb5\u0bb0\u0bbf \u0ba4\u0b95\u0bb5\u0bb2\u0bcd\u0b95\u0bb3\u0bc8 \u0baa\u0ba4\u0bbf\u0bb5\u0bc7\u0bb1\u0bcd\u0bb1\u0bb5\u0bc1\u0bae\u0bcd T4",
    "fields_document_verification_tax_proof_dialog_message": "\u0ba4\u0baf\u0bb5\u0bc1\u0b9a\u0bc6\u0baf\u0bcd\u0ba4\u0bc1, \u0bae\u0bc1\u0ba8\u0bcd\u0ba4\u0bc8\u0baf \u0b86\u0ba3\u0bcd\u0b9f\u0bbf\u0bb2\u0bbf\u0bb0\u0bc1\u0ba8\u0bcd\u0ba4\u0bc1 \u0b89\u0b99\u0bcd\u0b95\u0bb3\u0bcd T4 \u0b85\u0bb1\u0bbf\u0b95\u0bcd\u0b95\u0bc8\u0baf\u0bbf\u0ba9\u0bcd PDF \u0ba8\u0b95\u0bb2\u0bc8\u0baa\u0bcd \u0baa\u0ba4\u0bbf\u0bb5\u0bc7\u0bb1\u0bcd\u0bb1\u0bb5\u0bc1\u0bae\u0bcd.",
    "fields_document_verification_id_proof": "\u0b89\u0b99\u0bcd\u0b95\u0bb3\u0bcd \u0b90\u0b9f\u0bbf\u0baf\u0bbf\u0ba9\u0bcd \u0baa\u0bc1\u0b95\u0bc8\u0baa\u0bcd\u0baa\u0b9f\u0bae\u0bcd",
    "fields_document_verification_id_proof_message": "\u0b89\u0b99\u0bcd\u0b95\u0bb3\u0bcd \u0baa\u0b9f\u0bae\u0bcd \u0b87\u0bb0\u0bc1\u0b95\u0bcd\u0b95\u0bc1\u0bae\u0bcd \u0b92\u0bb0\u0bc1 \u0b85\u0bb0\u0b9a \u0b85\u0b9f\u0bc8\u0baf\u0bbe\u0bb3 \u0b85\u0b9f\u0bcd\u0b9f\u0baf\u0bc8 \u0baa\u0ba4\u0bbf\u0bb5\u0bc7\u0bb1\u0bcd\u0bb1\u0bae\u0bcd \u0b9a\u0bc6\u0baf\u0bcd\u0baf\u0bc1\u0b99\u0bcd\u0b95\u0bb3\u0bcd",
    "fields_document_verification_id_proof_dialog_message": "\u0ba4\u0baf\u0bb5\u0bc1\u0b9a\u0bc6\u0baf\u0bcd\u0ba4\u0bc1, \u0b89\u0b99\u0bcd\u0b95\u0bb3\u0bcd \u0b90\u0b9f\u0bbf\u0baf\u0bbf\u0ba9\u0bcd \u0baa\u0bc1\u0b95\u0bc8\u0baa\u0bcd\u0baa\u0b9f\u0ba4\u0bcd\u0ba4\u0bc8 \u0b8e\u0b99\u0bcd\u0b95\u0bb3\u0bc1\u0b95\u0bcd\u0b95\u0bc1 \u0bb5\u0bb4\u0b99\u0bcd\u0b95\u0bb5\u0bc1\u0bae\u0bcd. \u0b8e\u0bb2\u0bcd\u0bb2\u0bbe \u0ba4\u0b95\u0bb5\u0bb2\u0bcd\u0b95\u0bb3\u0bc1\u0bae\u0bcd \u0ba4\u0bc6\u0bb3\u0bbf\u0bb5\u0bbe\u0b95\u0ba4\u0bcd \u0ba4\u0bc6\u0bb0\u0bbf\u0baf\u0bc1\u0bae\u0bcd \u0bae\u0bb1\u0bcd\u0bb1\u0bc1\u0bae\u0bcd \u0baa\u0b9f\u0bbf\u0b95\u0bcd\u0b95\u0b95\u0bcd\u0b95\u0bc2\u0b9f\u0bbf\u0baf\u0bb5\u0bc8 \u0b8e\u0ba9\u0bcd\u0baa\u0ba4\u0bc8 \u0b89\u0bb1\u0bc1\u0ba4\u0bbf\u0baa\u0bcd\u0baa\u0b9f\u0bc1\u0ba4\u0bcd\u0ba4\u0bbf\u0b95\u0bcd \u0b95\u0bca\u0bb3\u0bcd\u0bb3\u0bc1\u0b99\u0bcd\u0b95\u0bb3\u0bcd.",
    "fields_document_verification_selfie_id_proof": "\u0b90\u0b9f\u0bbf\u0baf\u0bc1\u0b9f\u0ba9\u0bcd \u0b9a\u0bc6\u0bb2\u0bcd\u0baa\u0bbf",
    "fields_document_verification_selfie_id_proof_message": "\u0ba4\u0baf\u0bb5\u0bc1\u0b9a\u0bc6\u0baf\u0bcd\u0ba4\u0bc1, \u0b89\u0b99\u0bcd\u0b95\u0bb3\u0bcd \u0bb5\u0bb2\u0bc8 \u0b95\u0bc7\u0bae\u0bb0\u0bbe\u0bb5\u0bc8\u0baa\u0bcd \u0baa\u0baf\u0ba9\u0bcd\u0baa\u0b9f\u0bc1\u0ba4\u0bcd\u0ba4\u0bbf \u0b89\u0b99\u0bcd\u0b95\u0bb3\u0bcd \u0b90\u0b9f\u0bbf\u0baf\u0bc1\u0b9f\u0ba9\u0bcd \u0b9a\u0bc6\u0bb2\u0bcd\u0baa\u0bbf \u0b8e\u0b9f\u0bc1\u0ba4\u0bcd\u0ba4\u0bc1\u0b95\u0bcd \u0b95\u0bca\u0bb3\u0bcd\u0bb3\u0bc1\u0b99\u0bcd\u0b95\u0bb3\u0bcd. \u0b89\u0b99\u0bcd\u0b95\u0bb3\u0bcd \u0b9a\u0bbe\u0ba4\u0ba9\u0ba4\u0bcd\u0ba4\u0bbf\u0bb2\u0bcd \u0bb5\u0bb2\u0bc8 \u0b95\u0bc7\u0bae\u0bb0\u0bbe \u0b87\u0bb2\u0bcd\u0bb2\u0bc8\u0baf\u0bc6\u0ba9\u0bcd\u0bb1\u0bbe\u0bb2\u0bcd, \u0b89\u0b99\u0bcd\u0b95\u0bb3\u0bcd \u0ba4\u0bca\u0bb2\u0bc8\u0baa\u0bc7\u0b9a\u0bbf \u0b85\u0bb2\u0bcd\u0bb2\u0ba4\u0bc1 \u0b9f\u0bc7\u0baa\u0bcd\u0bb2\u0bc6\u0b9f\u0bcd\u0b9f\u0bbf\u0bb2\u0bbf\u0bb0\u0bc1\u0ba8\u0bcd\u0ba4\u0bc1 \u0b87\u0ba8\u0bcd\u0ba4 \u0baa\u0b9f\u0bbf\u0ba8\u0bbf\u0bb2\u0bc8\u0baf\u0bc8 \u0bae\u0bc1\u0b9f\u0bbf\u0b95\u0bcd\u0b95 \u0bae\u0bc1\u0b9f\u0bbf\u0baf\u0bc1\u0bae\u0bcd. \u0b8e\u0bb2\u0bcd\u0bb2\u0bbe \u0ba4\u0b95\u0bb5\u0bb2\u0bcd\u0b95\u0bb3\u0bc1\u0bae\u0bcd, \u0b89\u0b99\u0bcd\u0b95\u0bb3\u0bcd \u0bae\u0bc1\u0b95\u0bae\u0bc1\u0bae\u0bcd \u0ba4\u0bc6\u0bb0\u0bbf\u0baf\u0bc1\u0bae\u0bcd \u0b8e\u0ba9\u0bcd\u0baa\u0ba4\u0bc8 \u0b89\u0bb1\u0bc1\u0ba4\u0bbf\u0baa\u0bcd\u0baa\u0b9f\u0bc1\u0ba4\u0bcd\u0ba4\u0bbf\u0b95\u0bcd \u0b95\u0bca\u0bb3\u0bcd\u0bb3\u0bc1\u0b99\u0bcd\u0b95\u0bb3\u0bcd, \u0bae\u0bc7\u0bb2\u0bc1\u0bae\u0bcd \u0baa\u0bc1\u0b95\u0bc8\u0baa\u0bcd\u0baa\u0b9f\u0ba4\u0bcd\u0ba4\u0bbf\u0bb2\u0bcd \u0ba8\u0bb2\u0bcd\u0bb2 \u0ba4\u0bb0\u0bae\u0bcd \u0b89\u0bb3\u0bcd\u0bb3\u0ba4\u0bc1.",
    "fields_document_verification_selfie_id_proof_dialog_message": "\u0ba4\u0baf\u0bb5\u0bc1\u0b9a\u0bc6\u0baf\u0bcd\u0ba4\u0bc1, \u0b89\u0b99\u0bcd\u0b95\u0bb3\u0bcd \u0b90\u0b9f\u0bbf\u0baf\u0bc1\u0b9f\u0ba9\u0bcd \u0b9a\u0bc6\u0bb2\u0bcd\u0baa\u0bbf \u0b9a\u0bc6\u0baf\u0bcd\u0baf\u0bc1\u0b99\u0bcd\u0b95\u0bb3\u0bcd. \u0b89\u0b99\u0bcd\u0b95\u0bb3\u0bcd \u0b90\u0b9f\u0bbf \u0b89\u0b99\u0bcd\u0b95\u0bb3\u0bcd \u0bae\u0bc1\u0b95\u0ba4\u0bcd\u0ba4\u0bbf\u0bb1\u0bcd\u0b95\u0bc1 \u0b85\u0bb0\u0bc1\u0b95\u0bbf\u0bb2\u0bcd \u0b87\u0bb0\u0bc1\u0baa\u0bcd\u0baa\u0ba4\u0bc8\u0baf\u0bc1\u0bae\u0bcd, \u0b85\u0ba9\u0bc8\u0ba4\u0bcd\u0ba4\u0bc1 \u0ba4\u0b95\u0bb5\u0bb2\u0bcd\u0b95\u0bb3\u0bc1\u0bae\u0bcd \u0ba4\u0bc6\u0bb3\u0bbf\u0bb5\u0bbe\u0b95\u0b95\u0bcd \u0b95\u0bbe\u0ba3\u0b95\u0bcd\u0b95\u0bc2\u0b9f\u0bbf\u0baf\u0ba4\u0bbe\u0b95\u0bb5\u0bc1\u0bae\u0bcd \u0baa\u0b9f\u0bbf\u0b95\u0bcd\u0b95\u0b95\u0bcd\u0b95\u0bc2\u0b9f\u0bbf\u0baf\u0ba4\u0bbe\u0b95\u0bb5\u0bc1\u0bae\u0bcd \u0b87\u0bb0\u0bc1\u0baa\u0bcd\u0baa\u0ba4\u0bc8 \u0b89\u0bb1\u0bc1\u0ba4\u0bbf\u0b9a\u0bc6\u0baf\u0bcd\u0b95.",
    "fields_document_verification_select_type_document": "\u0b8e\u0baa\u0bcd\u0baa\u0b9f\u0bbf\u0baa\u0bcd\u0baa\u0b9f\u0bcd\u0b9f \u0b86\u0bb5\u0ba3\u0ba4\u0bcd\u0ba4\u0bc8 \u0baa\u0ba4\u0bbf\u0bb5\u0bc7\u0bb1\u0bcd\u0bb1\u0bae\u0bcd \u0b9a\u0bc6\u0baf\u0bcd\u0baf \u0baa\u0bcb\u0b95\u0bbf\u0ba9\u0bcd\u0bb1\u0bbf\u0bb0\u0bcd\u0b95\u0bb3\u0bcd",
    "fields_document_verification_upload_utility_bill_title": "\u0baa\u0baf\u0ba9\u0bcd\u0baa\u0bbe\u0b9f\u0bcd\u0b9f\u0bc1 \u0bae\u0b9a\u0bcb\u0ba4\u0bbe \u0baa\u0ba4\u0bbf\u0bb5\u0bc7\u0bb1\u0bcd\u0bb1",
    "fields_document_verification_upload_utility_bill_message": "\u0b89\u0b99\u0bcd\u0b95\u0bb3\u0bcd \u0baa\u0baf\u0ba9\u0bcd\u0baa\u0bbe\u0b9f\u0bcd\u0b9f\u0bc1 \u0baa\u0bbf\u0bb2\u0bcd\u0b95\u0bb3\u0bcd \u0b8e\u0ba4\u0bc8\u0baf\u0bc1\u0bae\u0bcd PDF \u0bb5\u0b9f\u0bbf\u0bb5\u0ba4\u0bcd\u0ba4\u0bbf\u0bb2\u0bcd \u0baa\u0ba4\u0bbf\u0bb5\u0bc7\u0bb1\u0bcd\u0bb1\u0bb5\u0bc1\u0bae\u0bcd.",
    "fields_document_verification_upload_pay_stub_title": "\u0baa\u0bc7 \u0bb8\u0bcd\u0b9f\u0baa\u0bcd \u0baa\u0ba4\u0bbf\u0bb5\u0bc7\u0bb1\u0bcd\u0bb1\u0bb5\u0bc1\u0bae\u0bcd",
    "fields_document_verification_upload_pay_stub_message": "\u0ba4\u0baf\u0bb5\u0bc1\u0b9a\u0bc6\u0baf\u0bcd\u0ba4\u0bc1 \u0b89\u0b99\u0bcd\u0b95\u0bb3\u0bcd \u0b9a\u0bae\u0bcd\u0baa\u0bb3 \u0bb8\u0bcd\u0b9f\u0baa\u0bcd \u0b8e\u0ba4\u0bc8\u0baf\u0bc1\u0bae\u0bcd PDF \u0bb5\u0b9f\u0bbf\u0bb5\u0ba4\u0bcd\u0ba4\u0bbf\u0bb2\u0bcd \u0baa\u0ba4\u0bbf\u0bb5\u0bc7\u0bb1\u0bcd\u0bb1\u0bb5\u0bc1\u0bae\u0bcd.",
    "fields_document_verification_upload_bank_statement_title": "\u0bb5\u0b99\u0bcd\u0b95\u0bbf \u0b85\u0bb1\u0bbf\u0b95\u0bcd\u0b95\u0bc8\u0baf\u0bc8 \u0baa\u0ba4\u0bbf\u0bb5\u0bc7\u0bb1\u0bcd\u0bb1\u0bb5\u0bc1\u0bae\u0bcd",
    "fields_document_verification_upload_bank_statement_message": "\u0b89\u0b99\u0bcd\u0b95\u0bb3\u0bcd \u0bb5\u0b99\u0bcd\u0b95\u0bbf \u0b85\u0bb1\u0bbf\u0b95\u0bcd\u0b95\u0bc8\u0b95\u0bb3\u0bcd \u0b8e\u0ba4\u0bc8\u0baf\u0bc1\u0bae\u0bcd PDF \u0bb5\u0b9f\u0bbf\u0bb5\u0ba4\u0bcd\u0ba4\u0bbf\u0bb2\u0bcd \u0baa\u0ba4\u0bbf\u0bb5\u0bc7\u0bb1\u0bcd\u0bb1\u0bb5\u0bc1\u0bae\u0bcd.",
    "fields_document_verification_upload_loan_statement_title": "\u0b95\u0b9f\u0ba9\u0bcd \u0b85\u0bb1\u0bbf\u0b95\u0bcd\u0b95\u0bc8\u0baf\u0bc8 \u0baa\u0ba4\u0bbf\u0bb5\u0bc7\u0bb1\u0bcd\u0bb1\u0bb5\u0bc1\u0bae\u0bcd",
    "fields_document_verification_upload_loan_statement_message": "\u0b89\u0b99\u0bcd\u0b95\u0bb3\u0bcd \u0b95\u0b9f\u0ba9\u0bcd \u0b85\u0bb1\u0bbf\u0b95\u0bcd\u0b95\u0bc8\u0b95\u0bb3\u0bbf\u0bb2\u0bcd \u0b8f\u0ba4\u0bc7\u0ba9\u0bc1\u0bae\u0bcd \u0b92\u0ba9\u0bcd\u0bb1\u0bc8 PDF \u0bb5\u0b9f\u0bbf\u0bb5\u0ba4\u0bcd\u0ba4\u0bbf\u0bb2\u0bcd \u0baa\u0ba4\u0bbf\u0bb5\u0bc7\u0bb1\u0bcd\u0bb1\u0bb5\u0bc1\u0bae\u0bcd.",
    "fields_document_verification_upload_credit_card_statement_title": "\u0b95\u0b9f\u0ba9\u0bcd \u0b85\u0b9f\u0bcd\u0b9f\u0bc8 \u0b86\u0bb5\u0ba3\u0bae\u0bcd \u0baa\u0ba4\u0bbf\u0bb5\u0bc7\u0bb1\u0bcd\u0bb1\u0bae\u0bcd \u0b9a\u0bc6\u0baf\u0bcd\u0baf\u0bb5\u0bc1\u0bae\u0bcd",
    "fields_document_verification_upload_credit_card_statement_message": "\u0b89\u0b99\u0bcd\u0b95\u0bb3\u0bcd \u0b95\u0bbf\u0bb0\u0bc6\u0b9f\u0bbf\u0b9f\u0bcd \u0b95\u0bbe\u0bb0\u0bcd\u0b9f\u0bc1 \u0b85\u0bb1\u0bbf\u0b95\u0bcd\u0b95\u0bc8\u0baf\u0bbf\u0ba9\u0bcd \u0ba8\u0b95\u0bb2\u0bc8 \u0b8e\u0b99\u0bcd\u0b95\u0bb3\u0bc1\u0b95\u0bcd\u0b95\u0bc1 \u0bb5\u0bb4\u0b99\u0bcd\u0b95\u0bb5\u0bc1\u0bae\u0bcd. \u0ba8\u0bc0\u0b99\u0bcd\u0b95\u0bb3\u0bcd \u0b85\u0ba4\u0bc8\u0baa\u0bcd \u0baa\u0b9f\u0bae\u0bcd \u0b8e\u0b9f\u0bc1\u0b95\u0bcd\u0b95\u0bb2\u0bbe\u0bae\u0bcd \u0b85\u0bb2\u0bcd\u0bb2\u0ba4\u0bc1 \u0b92\u0bb0\u0bc1 \u0b95\u0bcb\u0baa\u0bcd\u0baa\u0bc8 PDF \u0bb5\u0b9f\u0bbf\u0bb5\u0ba4\u0bcd\u0ba4\u0bbf\u0bb2\u0bcd \u0baa\u0ba4\u0bbf\u0bb5\u0bc7\u0bb1\u0bcd\u0bb1\u0bb2\u0bbe\u0bae\u0bcd.",
    "fields_document_verification_upload_birth_cert_title": "\u0baa\u0bbf\u0bb1\u0baa\u0bcd\u0baa\u0bc1\u0b9a\u0bcd \u0b9a\u0bbe\u0ba9\u0bcd\u0bb1\u0bbf\u0ba4\u0bb4\u0bc8\u0baa\u0bcd \u0baa\u0ba4\u0bbf\u0bb5\u0bc7\u0bb1\u0bcd\u0bb1\u0bc1\u0b95",
    "fields_document_verification_upload_birth_cert_message": "\u0b89\u0b99\u0bcd\u0b95\u0bb3\u0bcd \u0baa\u0bbf\u0bb1\u0baa\u0bcd\u0baa\u0bc1\u0b9a\u0bcd \u0b9a\u0bbe\u0ba9\u0bcd\u0bb1\u0bbf\u0ba4\u0bb4\u0bc8 PDF \u0bb5\u0b9f\u0bbf\u0bb5\u0ba4\u0bcd\u0ba4\u0bbf\u0bb2\u0bcd \u0baa\u0ba4\u0bbf\u0bb5\u0bc7\u0bb1\u0bcd\u0bb1\u0bb5\u0bc1\u0bae\u0bcd.",
    "fields_document_verification_upload_marriage_cert_title": "\u0ba4\u0bbf\u0bb0\u0bc1\u0bae\u0ba3 \u0b9a\u0bbe\u0ba9\u0bcd\u0bb1\u0bbf\u0ba4\u0bb4\u0bc8 \u0baa\u0ba4\u0bbf\u0bb5\u0bc7\u0bb1\u0bcd\u0bb1\u0bb5\u0bc1\u0bae\u0bcd",
    "fields_document_verification_upload_marriage_cert_message": "\u0b89\u0b99\u0bcd\u0b95\u0bb3\u0bcd \u0ba4\u0bbf\u0bb0\u0bc1\u0bae\u0ba3 \u0b9a\u0bbe\u0ba9\u0bcd\u0bb1\u0bbf\u0ba4\u0bb4\u0bc8 PDF \u0bb5\u0b9f\u0bbf\u0bb5\u0ba4\u0bcd\u0ba4\u0bbf\u0bb2\u0bcd \u0baa\u0ba4\u0bbf\u0bb5\u0bc7\u0bb1\u0bcd\u0bb1\u0bb5\u0bc1\u0bae\u0bcd.",
    "fields_document_verification_upload_pr_card_title": "\u0ba8\u0bbf\u0bb0\u0ba8\u0bcd\u0ba4\u0bb0 \u0bb5\u0ba4\u0bbf\u0bb5\u0bbf\u0b9f \u0b85\u0b9f\u0bcd\u0b9f\u0bc8\u0baf\u0bc8 \u0baa\u0ba4\u0bbf\u0bb5\u0bc7\u0bb1\u0bcd\u0bb1\u0bb5\u0bc1\u0bae\u0bcd",
    "fields_document_verification_upload_pr_card_message": "\u0b89\u0b99\u0bcd\u0b95\u0bb3\u0bcd \u0ba8\u0bbf\u0bb0\u0ba8\u0bcd\u0ba4\u0bb0 \u0bb5\u0ba4\u0bbf\u0bb5\u0bbf\u0b9f \u0b85\u0b9f\u0bcd\u0b9f\u0bc8\u0baf\u0bc8 PDF \u0bb5\u0b9f\u0bbf\u0bb5\u0ba4\u0bcd\u0ba4\u0bbf\u0bb2\u0bcd \u0baa\u0ba4\u0bbf\u0bb5\u0bc7\u0bb1\u0bcd\u0bb1\u0bb5\u0bc1\u0bae\u0bcd.",
    "fields_document_verification_upload_driver_license_title": "\u0b93\u0b9f\u0bcd\u0b9f\u0bc1\u0ba8\u0bb0\u0bcd \u0b89\u0bb0\u0bbf\u0bae\u0ba4\u0bcd\u0ba4\u0bc8\u0baa\u0bcd \u0baa\u0ba4\u0bbf\u0bb5\u0bc7\u0bb1\u0bcd\u0bb1\u0bc1\u0b95",
    "fields_document_verification_upload_driver_license_message": "\u0b89\u0b99\u0bcd\u0b95\u0bb3\u0bcd \u0b9f\u0bbf\u0bb0\u0bc8\u0bb5\u0bb0\u0bcd \u0b89\u0bb0\u0bbf\u0bae\u0ba4\u0bcd\u0ba4\u0bc8 PDF \u0bb5\u0b9f\u0bbf\u0bb5\u0ba4\u0bcd\u0ba4\u0bbf\u0bb2\u0bcd \u0baa\u0ba4\u0bbf\u0bb5\u0bc7\u0bb1\u0bcd\u0bb1\u0bb5\u0bc1\u0bae\u0bcd.",
    "fields_document_verification_upload_temp_driver_license_title": "\u0ba4\u0bb1\u0bcd\u0b95\u0bbe\u0bb2\u0bbf\u0b95 \u0b93\u0b9f\u0bcd\u0b9f\u0bc1\u0ba8\u0bb0\u0bcd \u0b89\u0bb0\u0bbf\u0bae\u0ba4\u0bcd\u0ba4\u0bc8\u0baa\u0bcd \u0baa\u0ba4\u0bbf\u0bb5\u0bc7\u0bb1\u0bcd\u0bb1\u0bc1\u0b95",
    "fields_document_verification_upload_temp_driver_license_message": "\u0b89\u0b99\u0bcd\u0b95\u0bb3\u0bcd \u0ba4\u0bb1\u0bcd\u0b95\u0bbe\u0bb2\u0bbf\u0b95 \u0b93\u0b9f\u0bcd\u0b9f\u0bc1\u0ba8\u0bb0\u0bcd \u0b89\u0bb0\u0bbf\u0bae\u0ba4\u0bcd\u0ba4\u0bc8 PDF \u0bb5\u0b9f\u0bbf\u0bb5\u0ba4\u0bcd\u0ba4\u0bbf\u0bb2\u0bcd \u0baa\u0ba4\u0bbf\u0bb5\u0bc7\u0bb1\u0bcd\u0bb1\u0bb5\u0bc1\u0bae\u0bcd.",
    "fields_document_verification_upload_travel_visa_title": "\u0baa\u0baf\u0ba3 \u0bb5\u0bbf\u0b9a\u0bbe\u0bb5\u0bc8 \u0baa\u0ba4\u0bbf\u0bb5\u0bc7\u0bb1\u0bcd\u0bb1\u0bb5\u0bc1\u0bae\u0bcd",
    "fields_document_verification_upload_travel_visa_message": "\u0b89\u0b99\u0bcd\u0b95\u0bb3\u0bcd \u0baa\u0baf\u0ba3 \u0bb5\u0bbf\u0b9a\u0bbe\u0bb5\u0bc8 PDF \u0bb5\u0b9f\u0bbf\u0bb5\u0ba4\u0bcd\u0ba4\u0bbf\u0bb2\u0bcd \u0baa\u0ba4\u0bbf\u0bb5\u0bc7\u0bb1\u0bcd\u0bb1\u0bb5\u0bc1\u0bae\u0bcd.",
    "fields_document_verification_upload_passport_title": "\u0baa\u0bbe\u0bb8\u0bcd\u0baa\u0bcb\u0bb0\u0bcd\u0b9f\u0bcd\u0b9f\u0bc8 \u0baa\u0ba4\u0bbf\u0bb5\u0bc7\u0bb1\u0bcd\u0bb1\u0bc1\u0b95",
    "fields_document_verification_upload_passport_message": "\u0b89\u0b99\u0bcd\u0b95\u0bb3\u0bcd \u0baa\u0bbe\u0bb8\u0bcd\u0baa\u0bcb\u0bb0\u0bcd\u0b9f\u0bcd\u0b9f\u0bc8 PDF \u0bb5\u0b9f\u0bbf\u0bb5\u0ba4\u0bcd\u0ba4\u0bbf\u0bb2\u0bcd \u0baa\u0ba4\u0bbf\u0bb5\u0bc7\u0bb1\u0bcd\u0bb1\u0bb5\u0bc1\u0bae\u0bcd.",
    "fields_document_verification_upload_citizenship_cert_title": "\u0b95\u0bc1\u0b9f\u0bbf\u0baf\u0bc1\u0bb0\u0bbf\u0bae\u0bc8 \u0b9a\u0bbe\u0ba9\u0bcd\u0bb1\u0bbf\u0ba4\u0bb4\u0bc8\u0baa\u0bcd \u0baa\u0ba4\u0bbf\u0bb5\u0bc7\u0bb1\u0bcd\u0bb1\u0bc1\u0b95",
    "fields_document_verification_upload_citizenship_cert_message": "\u0b89\u0b99\u0bcd\u0b95\u0bb3\u0bcd \u0b95\u0bc1\u0b9f\u0bbf\u0baf\u0bc1\u0bb0\u0bbf\u0bae\u0bc8 \u0b9a\u0bbe\u0ba9\u0bcd\u0bb1\u0bbf\u0ba4\u0bb4\u0bc8 PDF \u0bb5\u0b9f\u0bbf\u0bb5\u0ba4\u0bcd\u0ba4\u0bbf\u0bb2\u0bcd \u0baa\u0ba4\u0bbf\u0bb5\u0bc7\u0bb1\u0bcd\u0bb1\u0bb5\u0bc1\u0bae\u0bcd.",
    "fields_document_verification_successfully_uploaded": "\u0b89\u0b99\u0bcd\u0b95\u0bb3\u0bcd \u0b86\u0bb5\u0ba3\u0bae\u0bcd \u0bb5\u0bc6\u0bb1\u0bcd\u0bb1\u0bbf\u0b95\u0bb0\u0bae\u0bbe\u0b95 \u0baa\u0ba4\u0bbf\u0bb5\u0bc7\u0bb1\u0bcd\u0bb1\u0baa\u0bcd\u0baa\u0b9f\u0bcd\u0b9f\u0ba4\u0bc1. \u0b8e\u0b99\u0bcd\u0b95\u0bb3\u0bcd \u0b86\u0ba4\u0bb0\u0bb5\u0bc1 \u0b95\u0bc1\u0bb4\u0bc1 \u0b85\u0ba4\u0bc8 \u0bae\u0ba4\u0bbf\u0baa\u0bcd\u0baa\u0bbe\u0baf\u0bcd\u0bb5\u0bc1 \u0b9a\u0bc6\u0baf\u0bcd\u0ba4\u0bc1 \u0b85\u0b99\u0bcd\u0b95\u0bc0\u0b95\u0bb0\u0bbf\u0b95\u0bcd\u0b95 24 \u0bae\u0ba3\u0bbf\u0ba8\u0bc7\u0bb0\u0bae\u0bcd \u0b86\u0b95\u0bb2\u0bbe\u0bae\u0bcd. \u0b87\u0ba4\u0bc1 \u0b9a\u0bc6\u0baf\u0bb2\u0bbe\u0b95\u0bcd\u0b95\u0baa\u0bcd\u0baa\u0b9f\u0bcd\u0b9f\u0ba4\u0bc1\u0bae\u0bcd \u0ba8\u0bbe\u0b99\u0bcd\u0b95\u0bb3\u0bcd \u0b89\u0b99\u0bcd\u0b95\u0bb3\u0bc1\u0b95\u0bcd\u0b95\u0bc1 \u0b85\u0bb1\u0bbf\u0bb5\u0bbf\u0baa\u0bcd\u0baa\u0bcb\u0bae\u0bcd.",
    "fields_pin_to_address_title": "\u0bae\u0bc1\u0b95\u0bb5\u0bb0\u0bbf\u0b95\u0bcd\u0b95\u0bc1 \u0baa\u0bbe\u0ba4\u0bc1\u0b95\u0bbe\u0baa\u0bcd\u0baa\u0bc1 \u0b95\u0bc1\u0bb1\u0bbf\u0baf\u0bc0\u0b9f\u0bc1",
    "fields_pin_to_address_message": "\u0b89\u0b99\u0bcd\u0b95\u0bb3\u0bcd \u0b89\u0ba3\u0bcd\u0bae\u0bc8\u0baf\u0bbe\u0ba9 \u0b95\u0bc1\u0b9f\u0bbf\u0baf\u0bbf\u0bb0\u0bc1\u0baa\u0bcd\u0baa\u0bc1 \u0bae\u0bc1\u0b95\u0bb5\u0bb0\u0bbf\u0baf\u0bc8 \u0b9a\u0bb0\u0bbf\u0baa\u0bbe\u0bb0\u0bcd\u0b95\u0bcd\u0b95, \u0b89\u0b99\u0bcd\u0b95\u0bb3\u0bcd \u0b90\u0b9f\u0bbf\u0baf\u0bbf\u0bb2\u0bcd \u0b95\u0bc1\u0bb1\u0bbf\u0baa\u0bcd\u0baa\u0bbf\u0b9f\u0baa\u0bcd\u0baa\u0b9f\u0bcd\u0b9f\u0bc1\u0bb3\u0bcd\u0bb3 \u0bae\u0bc1\u0b95\u0bb5\u0bb0\u0bbf\u0b95\u0bcd\u0b95\u0bc1 \u0b9a\u0bbf\u0bb1\u0baa\u0bcd\u0baa\u0bc1 \u0baa\u0bbf\u0ba9\u0bcd \u0b95\u0bc1\u0bb1\u0bbf\u0baf\u0bc0\u0b9f\u0bcd\u0b9f\u0bc8\u0b95\u0bcd \u0b95\u0bca\u0ba3\u0bcd\u0b9f \u0b92\u0bb0\u0bc1 \u0b95\u0b9f\u0bbf\u0ba4\u0ba4\u0bcd\u0ba4\u0bc8 \u0b85\u0ba9\u0bc1\u0baa\u0bcd\u0baa\u0bc1\u0bb5\u0bcb\u0bae\u0bcd. \u0b87\u0ba4\u0bc1 \u0bb5\u0bb4\u0b99\u0bcd\u0b95\u0baa\u0bcd\u0baa\u0b9f\u0bc1\u0bb5\u0ba4\u0bb1\u0bcd\u0b95\u0bc1 4 \u0ba8\u0bbe\u0b9f\u0bcd\u0b95\u0bb3\u0bcd \u0bb5\u0bb0\u0bc8 \u0b86\u0b95\u0bb2\u0bbe\u0bae\u0bcd.",
    "fields_pin_to_address_sub_message": "\u0ba8\u0bc0\u0b99\u0bcd\u0b95\u0bb3\u0bcd \u0baa\u0bbf\u0ba9\u0bcd \u0b95\u0bc1\u0bb1\u0bbf\u0baf\u0bc0\u0b9f\u0bcd\u0b9f\u0bc8\u0baa\u0bcd \u0baa\u0bc6\u0bb1\u0bcd\u0bb1\u0bb5\u0bc1\u0b9f\u0ba9\u0bcd, \u0ba8\u0bc0\u0b99\u0bcd\u0b95\u0bb3\u0bcd \u0b95\u0bcb\u0bb0\u0bbf\u0b95\u0bcd\u0b95\u0bc8\u0baf\u0bc8 \u0b85\u0ba9\u0bc1\u0baa\u0bcd\u0baa\u0bbf\u0baf \u0baa\u0bbf\u0ba9\u0bcd \u0ba4\u0bcb\u0ba9\u0bcd\u0bb1\u0bc1\u0bae\u0bcd \u0baa\u0bc1\u0bb2\u0ba4\u0bcd\u0ba4\u0bbf\u0bb2\u0bcd \u0b85\u0ba4\u0bc8 \u0b89\u0bb3\u0bcd\u0bb3\u0bbf\u0b9f\u0bb5\u0bc1\u0bae\u0bcd.",
    "fields_pin_to_address_pending_message": "\u0b95\u0bcb\u0baa\u0bcd\u0baa\u0bbf\u0bb2\u0bcd \u0b89\u0bb3\u0bcd\u0bb3 \u0b89\u0b99\u0bcd\u0b95\u0bb3\u0bcd \u0bae\u0bc1\u0b95\u0bb5\u0bb0\u0bbf\u0b95\u0bcd\u0b95\u0bc1 \u0baa\u0bbe\u0ba4\u0bc1\u0b95\u0bbe\u0baa\u0bcd\u0baa\u0bc1 \u0b95\u0bc1\u0bb1\u0bbf\u0baf\u0bc0\u0b9f\u0bcd\u0b9f\u0bc8\u0b95\u0bcd \u0b95\u0bca\u0ba3\u0bcd\u0b9f \u0b92\u0bb0\u0bc1 \u0b87\u0bae\u0bc6\u0baf\u0bbf\u0bb2\u0bc8 \u0ba8\u0bbe\u0b99\u0bcd\u0b95\u0bb3\u0bcd \u0b89\u0b99\u0bcd\u0b95\u0bb3\u0bc1\u0b95\u0bcd\u0b95\u0bc1 \u0b85\u0ba9\u0bc1\u0baa\u0bcd\u0baa\u0bbf\u0baf\u0bc1\u0bb3\u0bcd\u0bb3\u0bcb\u0bae\u0bcd. \u0ba8\u0bc0\u0b99\u0bcd\u0b95\u0bb3\u0bcd \u0b85\u0ba4\u0bc8 {countDownValue} \u0baa\u0bc6\u0bb1 \u0bb5\u0bc7\u0ba3\u0bcd\u0b9f\u0bc1\u0bae\u0bcd. \u0ba8\u0bc0\u0b99\u0bcd\u0b95\u0bb3\u0bcd \u0b85\u0ba4\u0bc8\u0baa\u0bcd \u0baa\u0bc6\u0bb1\u0bcd\u0bb1\u0ba4\u0bc1\u0bae\u0bcd, \u0b95\u0bc0\u0bb4\u0bc7 \u0b89\u0bb3\u0bcd\u0bb3 \u0b95\u0bc1\u0bb1\u0bbf\u0baf\u0bc0\u0b9f\u0bcd\u0b9f\u0bc8\u0b9a\u0bcd \u0b9a\u0bae\u0bb0\u0bcd\u0baa\u0bcd\u0baa\u0bbf\u0b95\u0bcd\u0b95\u0bb5\u0bc1\u0bae\u0bcd.",
    "fields_pin_to_address_pending_message_time_expired": "\u0b95\u0bcb\u0baa\u0bcd\u0baa\u0bbf\u0bb2\u0bcd \u0b89\u0bb3\u0bcd\u0bb3 \u0b89\u0b99\u0bcd\u0b95\u0bb3\u0bcd \u0bae\u0bc1\u0b95\u0bb5\u0bb0\u0bbf\u0b95\u0bcd\u0b95\u0bc1 \u0baa\u0bbe\u0ba4\u0bc1\u0b95\u0bbe\u0baa\u0bcd\u0baa\u0bc1 \u0b95\u0bc1\u0bb1\u0bbf\u0baf\u0bc0\u0b9f\u0bcd\u0b9f\u0bc8\u0b95\u0bcd \u0b95\u0bca\u0ba3\u0bcd\u0b9f \u0b92\u0bb0\u0bc1 \u0bae\u0bc6\u0baf\u0bbf\u0bb2\u0bc8 \u0ba8\u0bbe\u0b99\u0bcd\u0b95\u0bb3\u0bcd \u0b89\u0b99\u0bcd\u0b95\u0bb3\u0bc1\u0b95\u0bcd\u0b95\u0bc1 \u0b85\u0ba9\u0bc1\u0baa\u0bcd\u0baa\u0bbf\u0baf\u0bc1\u0bb3\u0bcd\u0bb3\u0bcb\u0bae\u0bcd. \u0ba8\u0bc0\u0b99\u0bcd\u0b95\u0bb3\u0bcd \u0b85\u0ba4\u0bc8\u0baa\u0bcd \u0baa\u0bc6\u0bb1\u0bcd\u0bb1\u0ba4\u0bc1\u0bae\u0bcd, \u0b95\u0bc0\u0bb4\u0bc7 \u0b89\u0bb3\u0bcd\u0bb3 \u0b95\u0bc1\u0bb1\u0bbf\u0baf\u0bc0\u0b9f\u0bcd\u0b9f\u0bc8\u0b9a\u0bcd \u0b9a\u0bae\u0bb0\u0bcd\u0baa\u0bcd\u0baa\u0bbf\u0b95\u0bcd\u0b95\u0bb5\u0bc1\u0bae\u0bcd.",
    "fields_pin_to_address_send_request": "\u0b95\u0bcb\u0bb0\u0bbf\u0b95\u0bcd\u0b95\u0bc8\u0baf\u0bc8 \u0b85\u0ba9\u0bc1\u0baa\u0bcd\u0baa\u0bb5\u0bc1\u0bae\u0bcd",
    "fields_pin_to_address_request_received": "\u0b89\u0b99\u0bcd\u0b95\u0bb3\u0bcd \u0b95\u0bcb\u0bb0\u0bbf\u0b95\u0bcd\u0b95\u0bc8 \u0baa\u0bc6\u0bb1\u0baa\u0bcd\u0baa\u0b9f\u0bcd\u0b9f\u0ba4\u0bc1!",
    "fields_pin_to_address_letter_was_sent": "\u0b89\u0b99\u0bcd\u0b95\u0bb3\u0bcd \u0bae\u0bc1\u0b95\u0bb5\u0bb0\u0bbf\u0b95\u0bcd\u0b95\u0bc1 6 \u0b87\u0bb2\u0b95\u0bcd\u0b95 \u0baa\u0bbf\u0ba9\u0bcd (PIN ) \u0b89\u0b9f\u0ba9\u0bcd \u0b92\u0bb0\u0bc1 \u0b95\u0b9f\u0bbf\u0ba4\u0ba4\u0bcd\u0ba4\u0bc8 \u0b85\u0ba9\u0bc1\u0baa\u0bcd\u0baa\u0bc1\u0b95\u0bbf\u0bb1\u0bcb\u0bae\u0bcd:",
    "fields_pin_to_address_once_letter_received": "\u0ba8\u0bc0\u0b99\u0bcd\u0b95\u0bb3\u0bcd \u0b85\u0ba4\u0bc8\u0baa\u0bcd \u0baa\u0bc6\u0bb1\u0bcd\u0bb1\u0bb5\u0bc1\u0b9f\u0ba9\u0bcd, \u0b89\u0b99\u0bcd\u0b95\u0bb3\u0bcd \u0b9f\u0bbe\u0bb7\u0bcd\u0baa\u0bcb\u0bb0\u0bcd\u0b9f\u0bbf\u0bb2\u0bcd \u0b89\u0bb3\u0bcd\u0bb3 \u0b87\u0ba3\u0bc8\u0baa\u0bcd\u0baa\u0bc8\u0baa\u0bcd \u0baa\u0baf\u0ba9\u0bcd\u0baa\u0b9f\u0bc1\u0ba4\u0bcd\u0ba4\u0bbf \u0b85\u0bb2\u0bcd\u0bb2\u0ba4\u0bc1 \u0ba8\u0bbf\u0bb2\u0bc8 3 \u0b9a\u0bb0\u0bbf\u0baa\u0bbe\u0bb0\u0bcd\u0baa\u0bcd\u0baa\u0bc1 \u0bae\u0bc2\u0bb2\u0bae\u0bcd PIN \u0b90 \u0b89\u0bb3\u0bcd\u0bb3\u0bbf\u0b9f\u0bb5\u0bc1\u0bae\u0bcd.",
    "fields_pin_to_address_pin_verified_title": "\u0b89\u0b99\u0bcd\u0b95\u0bb3\u0bcd \u0b9a\u0bb0\u0bbf\u0baa\u0bbe\u0bb0\u0bcd\u0baa\u0bcd\u0baa\u0bc1\u0b95\u0bcd\u0b95\u0bc1 \u0ba8\u0ba9\u0bcd\u0bb1\u0bbf",
    "fields_pin_to_address_pin_verified_message": "\u0b89\u0b99\u0bcd\u0b95\u0bb3\u0bcd \u0b9a\u0bc6\u0baf\u0bb2\u0bcd\u0baa\u0bbe\u0b9f\u0bc1 \u0bb5\u0bc6\u0bb1\u0bcd\u0bb1\u0bbf\u0b95\u0bb0\u0bae\u0bbe\u0b95 \u0b9a\u0bb0\u0bbf\u0baa\u0bbe\u0bb0\u0bcd\u0b95\u0bcd\u0b95\u0baa\u0bcd\u0baa\u0b9f\u0bcd\u0b9f\u0ba4\u0bc1.",
    "fields_pin_to_address_pin_code_txt_label": "\u0baa\u0bbe\u0ba4\u0bc1\u0b95\u0bbe\u0baa\u0bcd\u0baa\u0bc1 \u0b95\u0bc1\u0bb1\u0bbf\u0baf\u0bc0\u0b9f\u0bcd\u0b9f\u0bc8 \u0b89\u0bb3\u0bcd\u0bb3\u0bbf\u0b9f\u0bb5\u0bc1\u0bae\u0bcd",
    "fields_pin_to_address_submit_code": "\u0b95\u0bc1\u0bb1\u0bbf\u0baf\u0bc0\u0b9f\u0bcd\u0b9f\u0bc8\u0b9a\u0bcd \u0b9a\u0bae\u0bb0\u0bcd\u0baa\u0bcd\u0baa\u0bbf\u0b95\u0bcd\u0b95\u0bb5\u0bc1\u0bae\u0bcd",
    "groups_personality_verification_title": "\u0b86\u0bb3\u0bc1\u0bae\u0bc8 \u0b9a\u0bb0\u0bbf\u0baa\u0bbe\u0bb0\u0bcd\u0baa\u0bcd\u0baa\u0bc1",
    "groups_personality_verification_message": "\u0ba8\u0bbf\u0bb2\u0bc8 3 \u0b9a\u0bb0\u0bbf\u0baa\u0bbe\u0bb0\u0bcd\u0baa\u0bcd\u0baa\u0bc8 \u0bae\u0bc1\u0b9f\u0bbf\u0b95\u0bcd\u0b95, \u0b89\u0b99\u0bcd\u0b95\u0bb3\u0bcd \u0b85\u0ba9\u0bc1\u0baa\u0bcd\u0baa\u0bc1\u0bae\u0bcd \u0bb5\u0bb0\u0bae\u0bcd\u0baa\u0bc1\u0b95\u0bb3\u0bc8 \u0b85\u0ba4\u0bbf\u0b95\u0bb0\u0bbf\u0b95\u0bcd\u0b95 \u0ba8\u0bbe\u0b99\u0bcd\u0b95\u0bb3\u0bcd \u0b89\u0b99\u0bcd\u0b95\u0bb3\u0bbf\u0b9f\u0bae\u0bbf\u0bb0\u0bc1\u0ba8\u0bcd\u0ba4\u0bc1 \u0b9a\u0bbf\u0bb2 \u0b95\u0bc2\u0b9f\u0bc1\u0ba4\u0bb2\u0bcd \u0ba4\u0b95\u0bb5\u0bb2\u0bcd\u0b95\u0bb3\u0bc8\u0baa\u0bcd \u0baa\u0bc6\u0bb1 \u0bb5\u0bc7\u0ba3\u0bcd\u0b9f\u0bc1\u0bae\u0bcd. \u0b8e\u0bb2\u0bcd\u0bb2\u0bbe \u0ba4\u0bb0\u0bb5\u0bc1\u0bae\u0bcd \u0baa\u0bc1\u0b95\u0bc8\u0baa\u0bcd\u0baa\u0b9f\u0b99\u0bcd\u0b95\u0bb3\u0bc1\u0bae\u0bcd \u0baa\u0bbe\u0ba4\u0bc1\u0b95\u0bbe\u0b95\u0bcd\u0b95\u0baa\u0bcd\u0baa\u0b9f\u0bc1\u0bae\u0bcd, \u0bb5\u0bc7\u0bb1\u0bc1 \u0b8e\u0ba8\u0bcd\u0ba4 \u0bae\u0bc2\u0ba9\u0bcd\u0bb1\u0bbe\u0bae\u0bcd \u0ba4\u0bb0\u0baa\u0bcd\u0baa\u0bc1 \u0ba8\u0bbf\u0bb1\u0bc1\u0bb5\u0ba9\u0b99\u0bcd\u0b95\u0bb3\u0bc1\u0b9f\u0ba9\u0bc1\u0bae\u0bcd \u0baa\u0b95\u0bbf\u0bb0\u0baa\u0bcd\u0baa\u0b9f\u0bbe\u0ba4\u0bc1.",
    "groups_personality_verification_time": "96 \u0bae\u0ba3\u0bbf \u0ba8\u0bc7\u0bb0\u0bae\u0bcd \u0b86\u0b95\u0bb2\u0bbe\u0bae\u0bcd",
    "groups_employment_verification_title": "\u0bb5\u0bc7\u0bb2\u0bc8 \u0b9a\u0bb0\u0bbf\u0baa\u0bbe\u0bb0\u0bcd\u0baa\u0bcd\u0baa\u0bc1",
    "groups_employment_verification_message": "\u0ba8\u0bbf\u0bb2\u0bc8 3 \u0b9a\u0bb0\u0bbf\u0baa\u0bbe\u0bb0\u0bcd\u0baa\u0bcd\u0baa\u0bc8 \u0bae\u0bc1\u0b9f\u0bbf\u0b95\u0bcd\u0b95, \u0b89\u0b99\u0bcd\u0b95\u0bb3\u0bcd \u0b85\u0ba9\u0bc1\u0baa\u0bcd\u0baa\u0bc1\u0bae\u0bcd \u0bb5\u0bb0\u0bae\u0bcd\u0baa\u0bc1\u0b95\u0bb3\u0bc8 \u0b85\u0ba4\u0bbf\u0b95\u0bb0\u0bbf\u0b95\u0bcd\u0b95 \u0ba8\u0bbe\u0b99\u0bcd\u0b95\u0bb3\u0bcd \u0b89\u0b99\u0bcd\u0b95\u0bb3\u0bbf\u0b9f\u0bae\u0bbf\u0bb0\u0bc1\u0ba8\u0bcd\u0ba4\u0bc1 \u0b9a\u0bbf\u0bb2 \u0b95\u0bc2\u0b9f\u0bc1\u0ba4\u0bb2\u0bcd \u0ba4\u0b95\u0bb5\u0bb2\u0bcd\u0b95\u0bb3\u0bc8\u0baa\u0bcd \u0baa\u0bc6\u0bb1 \u0bb5\u0bc7\u0ba3\u0bcd\u0b9f\u0bc1\u0bae\u0bcd. \u0b8e\u0bb2\u0bcd\u0bb2\u0bbe \u0ba4\u0bb0\u0bb5\u0bc1\u0bae\u0bcd \u0baa\u0bc1\u0b95\u0bc8\u0baa\u0bcd\u0baa\u0b9f\u0b99\u0bcd\u0b95\u0bb3\u0bc1\u0bae\u0bcd \u0baa\u0bbe\u0ba4\u0bc1\u0b95\u0bbe\u0b95\u0bcd\u0b95\u0baa\u0bcd\u0baa\u0b9f\u0bc1\u0bae\u0bcd, \u0bb5\u0bc7\u0bb1\u0bc1 \u0b8e\u0ba8\u0bcd\u0ba4 \u0bae\u0bc2\u0ba9\u0bcd\u0bb1\u0bbe\u0bae\u0bcd \u0ba4\u0bb0\u0baa\u0bcd\u0baa\u0bc1 \u0ba8\u0bbf\u0bb1\u0bc1\u0bb5\u0ba9\u0b99\u0bcd\u0b95\u0bb3\u0bc1\u0b9f\u0ba9\u0bc1\u0bae\u0bcd \u0baa\u0b95\u0bbf\u0bb0\u0baa\u0bcd\u0baa\u0b9f\u0bbe\u0ba4\u0bc1.",
    "groups_employment_verification_time": "48 \u0bae\u0ba3\u0bbf \u0ba8\u0bc7\u0bb0\u0bae\u0bcd \u0b86\u0b95\u0bb2\u0bbe\u0bae\u0bcd",
    "groups_videocall_verification_title": "\u0bb5\u0bc0\u0b9f\u0bbf\u0baf\u0bcb \u0b85\u0bb4\u0bc8\u0baa\u0bcd\u0baa\u0bc1 \u0b9a\u0bb0\u0bbf\u0baa\u0bbe\u0bb0\u0bcd\u0baa\u0bcd\u0baa\u0bc1 \u0bb5\u0bb4\u0bbf\u0baf\u0bbe\u0b95 \u0b89\u0b99\u0bcd\u0b95\u0bb3\u0bcd \u0b90\u0b9f\u0bbf\u0baf\u0bc8 \u0b9a\u0bb0\u0bbf\u0baa\u0bbe\u0bb0\u0bcd\u0b95\u0bcd\u0b95\u0bb5\u0bc1\u0bae\u0bcd",
    "groups_videocall_verification_message": "\u0b8e\u0b99\u0bcd\u0b95\u0bb3\u0bcd \u0b86\u0ba4\u0bb0\u0bb5\u0bc1 \u0bae\u0bc1\u0b95\u0bb5\u0bb0\u0bcd\u0b95\u0bb3\u0bbf\u0bb2\u0bcd \u0b92\u0bb0\u0bc1\u0bb5\u0bb0\u0bc1\u0b9f\u0ba9\u0bcd \u0b86\u0ba9\u0bcd\u0bb2\u0bc8\u0ba9\u0bcd \u0bb5\u0bc0\u0b9f\u0bbf\u0baf\u0bcb \u0b85\u0bb4\u0bc8\u0baa\u0bcd\u0baa\u0bc1 \u0bae\u0bc2\u0bb2\u0bae\u0bcd \u0b89\u0b99\u0bcd\u0b95\u0bb3\u0bcd \u0ba8\u0bbf\u0bb2\u0bc8 3 \u0b9a\u0bb0\u0bbf\u0baa\u0bbe\u0bb0\u0bcd\u0baa\u0bcd\u0baa\u0bc8 \u0bae\u0bc1\u0b9f\u0bbf\u0b95\u0bcd\u0b95 \u0bae\u0bc1\u0b9f\u0bbf\u0baf\u0bc1\u0bae\u0bcd. \u0b87\u0ba8\u0bcd\u0ba4 \u0b85\u0bb4\u0bc8\u0baa\u0bcd\u0baa\u0bc1\u0b95\u0bcd\u0b95\u0bc1 10 \u0ba8\u0bbf\u0bae\u0bbf\u0b9f\u0b99\u0bcd\u0b95\u0bb3\u0bcd \u0b86\u0b95\u0bb2\u0bbe\u0bae\u0bcd, \u0bae\u0bc7\u0bb2\u0bc1\u0bae\u0bcd \u0b87\u0ba3\u0bc8\u0baf\u0bae\u0bcd \u0bae\u0bb1\u0bcd\u0bb1\u0bc1\u0bae\u0bcd \u0b95\u0bc7\u0bae\u0bb0\u0bbe\u0bb5\u0bbf\u0bb1\u0bcd\u0b95\u0bbe\u0ba9 \u0b89\u0b99\u0bcd\u0b95\u0bb3\u0bcd \u0b85\u0ba3\u0bc1\u0b95\u0bb2\u0bcd \u0ba4\u0bc7\u0bb5\u0bc8\u0baa\u0bcd\u0baa\u0b9f\u0bc1\u0bae\u0bcd. \u0bae\u0bc7\u0bb2\u0bc1\u0bae\u0bcd, \u0b9a\u0bb0\u0bbf\u0baa\u0bbe\u0bb0\u0bcd\u0baa\u0bcd\u0baa\u0bc1\u0b95\u0bcd\u0b95\u0bc1 \u0b89\u0b99\u0bcd\u0b95\u0bb3\u0bcd \u0b90\u0b9f\u0bbf \u0ba4\u0baf\u0bbe\u0bb0\u0bbe\u0b95 \u0b89\u0bb3\u0bcd\u0bb3\u0ba4\u0bbe \u0b8e\u0ba9\u0bcd\u0baa\u0ba4\u0bc8 \u0b89\u0bb1\u0bc1\u0ba4\u0bbf\u0baa\u0bcd\u0baa\u0b9f\u0bc1\u0ba4\u0bcd\u0ba4\u0bbf\u0b95\u0bcd \u0b95\u0bca\u0bb3\u0bcd\u0bb3\u0bc1\u0b99\u0bcd\u0b95\u0bb3\u0bcd.",
    "groups_videocall_verification_time": "\u0b89\u0b9f\u0ba9\u0b9f\u0bbf \u0b9a\u0bb0\u0bbf\u0baa\u0bbe\u0bb0\u0bcd\u0baa\u0bcd\u0baa\u0bc1"
}